{
  "posts": [
    {
      "pid": "52576878",
      "uid": "561239",
      "dateline": "1474952181",
      "message": "[font=Trebuchet MS][size=1][color=transparent]       [/color]\n\n[align=center][IMG]http://hackforums.news/assets/v3/310.png[/IMG][/align]\n\n[color=transparent]       [/color]\n\n[align=center][img]http://www.hackforums.news/assets/v3/Headlines/iHydra.png[/img][/align]\n\n[b][color=white]No Marketplace Threads in GFX Contests[/color][/b]\nAs a reminder, all marketplace threads should be kept in the Marketplace forum. For graphics, there is a dedicated subforum in the marketplace that users can request or offer their services for money. The GFX Contests subforum is strictly for contests just like how the regular contests subforum is (and giveaways).[i][size=x-small][url=http://hackforums.net/showthread.php?tid=5413804] >>Source[/url][/size][/i]\n\n[color=transparent]       [/color]\n\n[align=center][url=http://hackforums.net/member.php?action=profile&uid=2577525][img]http://i.imgur.com/W4AjjOA.png[/img][/url][/align][color=white][b]Site Statistics[/b][/color] \n [list][*][sp=[b]Total[/b]] \n [list][*][u]Posts:[/u] 52,580,872 ( [color=#32CD32]+0.17%[/color] ) \n [*][u]Threads:[/u] 3,636,433 ( [color=#32CD32]+0.2%[/color] ) \n [*][u]Members:[/u] 3,298,229 ( [color=#32CD32]+2.21%[/color] )[/list][/sp][/list] \n [list][*][sp=[b]Average[/b]] \n [list][*][u]Daily Posts:[/u] 13846.53 ( [color=#FF0000]-0.04%[/color] ) \n [*][u]Daily Threads:[/u] 957.61 ( [color=#FF0000]-0.01%[/color] ) \n [*][u]Daily New Members:[/u] 868.55 ( [color=#32CD32]+2%[/color] ) \n [*][u]Posts Per Member:[/u] 15.94 ( [color=#FF0000]-2.03%[/color] ) \n [*][u]Replies Per Thread:[/u] 13.46 ( [color=#FF0000]0%[/color] )[/list][/sp][/list] \n [b][color=white]Ban Statistics[/color][/b] \n [list][*][sp=[b]Last Weeks Bans[/b]] \n [list][*][u]Staff Bans:[/u] 67 \n [list][*][i]... Change from Last Edition:[/i] [color=#32CD32]+35[/color][/list][/list] \n [list][*][u]Vacation Bans:[/u] 8 \n [list][*][i]... Change from Last Edition:[/i] [color=#FFD700]~[/color][/list][/list] \n [list][*][u]Combined Bans:[/u] 75 \n [list][*][i]... Change from Last Edition:[/i] [color=#32CD32]+35[/color][/list][/list][/sp][/list] \n [color=white][b]Forum Counts[/b][/color] \n [list][*][sp=[b]Tab Counts[/b]] \n [list][*][b]Notable Sections[/b] \n [list][*][u][url=http://hackforums.net/forumdisplay.php?fid=25][b]Lounge[/b][/url] Threads:[/u] 510,723 ( [color=#32CD32]+0.17%[/color] ) \n [*][u][url=http://hackforums.net/forumdisplay.php?fid=25][b]Lounge[/b][/url] Posts:[/u] 7,612,796 ( [color=#32CD32]+0.15%[/color] ) \n [*][u][url=http://hackforums.net/forumdisplay.php?fid=2][b]RANF[/b][/url] Threads:[/u] 66,813 ( [color=#32CD32]+0.13%[/color] ) \n [*][u][url=http://hackforums.net/forumdisplay.php?fid=2][b]RANF[/b][/url] Posts:[/u] 1,071,873 ( [color=#32CD32]+0.1%[/color] )[/list][/list] \n [list][*][b]Common[/b] \n [list][*][u]Threads:[/u] 701,093 ( [color=#FF0000]-11.36%[/color] ) \n [*][u]Posts:[/u] 11,898,559 ( [color=#32CD32]+0.18%[/color] )[/list][/list] \n [list][*][b]Hack[/b] \n [list][*][u]Threads:[/u] 672,834 ( [color=#32CD32]+0.14%[/color] ) \n [*][u]Posts:[/u] 5,874,153 ( [color=#32CD32]+0.13%[/color] )[/list][/list] \n [list][*][b]Tech[/b] \n [list][*][u]Threads:[/u] 204,855 ( [color=#32CD32]+0.09%[/color] ) \n [*][u]Posts:[/u] 1,397,686 ( [color=#FF0000]-18.76%[/color] )[/list][/list] \n [list][*][b]Code[/b] \n [list][*][u]Threads:[/u] 165,792 ( [color=#FF0000]NaN%[/color] ) \n [*][u]Posts:[/u] 1,505,600 ( [color=#32CD32]+5.95%[/color] )[/list][/list] \n [list][*][b]Game[/b] \n [list][*][u]Threads:[/u] 448,771 ( [color=#32CD32]+0.66%[/color] ) \n [*][u]Posts:[/u] 46,487,898 ( [color=#32CD32]+905.51%[/color] )[/list][/list] \n [list][*][b]Groups[/b] \n [list][*][u]Threads:[/u] 7,300 ( [color=#32CD32]+0.21%[/color] ) \n [*][u]Posts:[/u] 318,800 ( [color=#32CD32]+0.22%[/color] )[/list][/list] \n [list][*][b]Web[/b] \n [list][*][u]Threads:[/u] 81,881 ( [color=#32CD32]+0.12%[/color] ) \n [*][u]Posts:[/u] 593,046 ( [color=#32CD32]+0.1%[/color] )[/list][/list] \n [list][*][b]GFX[/b] \n [list][*][u]Threads:[/u] 133,041 ( [color=#32CD32]+0.08%[/color] ) \n [*][u]Posts:[/u] 993,650 ( [color=#32CD32]+0.07%[/color] )[/list][/list] \n [list][*][b]Market[/b] \n [list][*][u]Threads:[/u] 975,804 ( [color=#32CD32]+0.22%[/color] ) \n [*][u]Posts:[/u] 8,817,878 ( [color=#32CD32]+0.14%[/color] )[/list][/list] \n [list][*][b]Money[/b] \n [list][*][u]Threads:[/u] 138,647 ( [color=#FF0000]NaN%[/color] ) \n [*][u]Posts:[/u] 1,817,601 ( [color=#FF0000]-5.19%[/color] )[/list][/list][/list] \n [/sp] \n [color=white][b]Membership Counts[/b][/color] \n [list][*][sp=[b]Groups[/b]] \n [list][*][b]Null[/b] \n [list][*]25 Members ( [color=#FFD700]~[/color] )[/list] \n [*][b]Nightmare[/b] \n [list][*]66 Members ( [color=#32CD32]+6[/color] )[/list] \n [*][b]Red Lions[/b] \n [list][*]17 Members ( [color=#32CD32]+4[/color] )[/list] \n [*][b]Dawn[/b] \n [list][*]20 Members ( [color=#FF0000]-2[/color] )[/list] \n [*][b]Enigma[/b] \n [list][*]63 Members ( [color=#32CD32]+4[/color] )[/list] \n [*][b]Illuminati[/b] \n [list][*]27 Members ( [color=#FFD700]~[/color] )[/list] \n [*][b]Synergy[/b] \n [list][*]70 Members ( [color=#FF0000]-15[/color] )[/list] \n [*][b]Echo[/b] \n [list][*]46 Members ( [color=#FF0000]-4[/color] )[/list] \n [*][b]Fusion[/b] \n [list][*]175 Members ( [color=#FF0000]-10[/color] )[/list] \n [*][b]The Order[/b] \n [list][*]49 Members ( [color=#32CD32]+5[/color] )[/list] \n [*][b]Riptide[/b] \n [list][*]55 Members ( [color=#FFD700]~[/color] )[/list] \n [*][b]Eternal[/b] \n [list][*]27 Members ( [color=#FF0000]-117[/color] )[/list] \n [*][b]Titans[/b] \n [list][*]32 Members ( [color=#FFD700]~[/color] )[/list] \n [*][b]Royalty[/b] \n [list][*]40 Members ( [color=#FF0000]-1[/color] )[/list] \n [*][b]Legends[/b] \n [list][*]24 Members ( [color=#FF0000]-1[/color] )[/list][/list][/sp][/list]\n\n[color=transparent]       [/color]\n\n[align=center][img]http://hackforums.news/assets/v3/GroupNews.png[/img][/align]\n\n[b][color=white]Group Changes[/color][/b]\n[list]\n[*][url=http://hackforums.net/member.php?action=profile&uid=2194640][color=white][b]Nex+[/b][/color][/url] has re-branded Eternal into Incentive.\n[/list]\n\n[b][color=white]Leadership Changes[/color][/b]\n[list]\n[*][url=http://hackforums.net/member.php?action=profile&uid=1087518][color=white][b].Reef[/b][/color][/url] is now a leader of Incentive.\n[*][url=http://hackforums.net/member.php?action=profile&uid=3049211][color=white][b]Baphomet™[/b][/color][/url] is now a leader of Illuminati.\n[*][url=http://hackforums.net/member.php?action=profile&uid=2867762][color=white][b]LUCKYMR7[/b][/color][/url] is no longer a leader of Incentive.\n[*][url=http://hackforums.net/member.php?action=profile&uid=341617][color=white][b]Tutelary[/b][/color][/url] is no longer a leader of Illuminati.\n[/list]\n\n[b][color=white]Group Recruitments[/color][/b]\n[list]\n[*][url=http://hackforums.net/showthread.php?tid=5158658][b]Hack Forums News // Recruitment[/b][/url]\n[*][url=http://hackforums.net/showthread.php?tid=5377955][b][Official Group] Apex | Recruitment #2 [/b][/url]\n[*][url=http://hackforums.net/showthread.php?tid=5128494][b][OFFICIAL] Fusion Recruitment[/b][/url]\n[*][url=http://hackforums.net/showthread.php?tid=5416735][b]Incentive | General and Mentorship Recruitment [/b][/url]\n[*][url=http://hackforums.net/showthread.php?tid=5376863][b]Illuminati | Novus Ordo Seclorum | Apply[/b][/url]\n[*][url=http://hackforums.net/showthread.php?tid=5414206][b]Nightmare - Lounge Whores[/b][/url]\n[*][url=http://hackforums.net/showthread.php?tid=5403173][b][Nightmare] The Underworld Recruitment - Private Discord, Crypto Currency, Pump&Dumps[/b][/url]\n[*][url=http://hackforums.net/showthread.php?tid=5261678][b]Riptide ~ Recruitment[/b][/url]\n[*][url=http://hackforums.net/showthread.php?tid=5381652][b]Riptide Recruitment for all sectors[/b][/url]\n[*][url=http://hackforums.net/showthread.php?tid=5400985][b]Riptide Student Programme[/b][/url]\n[*][url=http://hackforums.net/showthread.php?tid=5333890][b][Royalty] Recruitment - General - Official -][/b][/url]\n[*][url=http://hackforums.net/showthread.php?tid=5392049][b]Synergy | Gaming Recruitment | Xbox One, PS4, PC [NA & EU][/b][/url]\n[/list]\n\n[b][color=white]Informational and Buy-in Threads[/color][/b]\n[list]\n[*][url=http://hackforums.net/showthread.php?tid=5260267][b][Official Group] Apex - Information[/b][/url]\n[*][url=http://hackforums.net/showthread.php?tid=5097281][b]Enigma | General Information[/b][/url]\n[*][url=http://hackforums.net/showthread.php?tid=5368990][b][Official Group] Enigma - Leadership Spot - Roger Waters[/b][/url]\n[*][url=http://hackforums.net/showthread.php?tid=5400771][b][Official Group] Enigma - Leadership Spot - Tear[/b][/url]\n[*][url=http://hackforums.net/showthread.php?tid=5127772][b][OFFICIAL] Fusion Official Information[/b][/url]\n[*][url=http://hackforums.net/showthread.php?tid=5412533][b][Official Group] \"Incentive\" Information Thread. Coming this sunday.[/b][/url]\n[*][url=http://hackforums.net/showthread.php?tid=5267722][b][NEW UB] [Official Group] > {LEGENDS } < General Information Thread[/b][/url]\n[*][url=http://hackforums.net/showthread.php?tid=5253595][b]Riptide ~ General Information[/b][/url]\n[*][url=http://hackforums.net/showthread.php?tid=5338909][b][OFFICIAL] Synergy | How To Join | General Information[/b][/url]\n[*][url=http://hackforums.net/showthread.php?tid=5378225][b][For Sale] The Order - Gambling SF (SF Re-brand + Mod Status)[/b][/url]\n[*][url=http://hackforums.net/showthread.php?tid=5299429][b][Official Group] The Order - Remastered[/b][/url]\n[*][url=http://hackforums.net/showthread.php?tid=4456035][b]Titans | Official Group\n[/b][/url]\n[/list]\n\n[b][color=white]Groups For Sale[/color][/b]\n[list]\n[*][url=http://hackforums.net/showthread.php?tid=5408316][b][Official Group Sale][/b][/url]\n[/list]\n\n[align=left][size=x-small][color=white][b]*[/b][/color]As of the Friday prior to release.[/size][/align]\n\n[color=transparent]       [/color]\n\n[align=center][url=http://hackforums.net/member.php?action=profile&uid=525019][img]http://www.hackforums.news/assets/v3/UserNews.png[/img][/url][/align]\n\n[color=white][b]User News[/b][/color]\n[list]\n[*] [url=http://hackforums.net/member.php?action=profile&uid=3129680][color=white][b]Riyu[/b][/color][/url] has reached 5,000 posts. \n[*] [url=http://hackforums.net/member.php?action=profile&uid=1093501][color=white][b]Roger Waters[/b][/color][/url] has reached 20,000 posts, again...\n[/list]\n\n[color=white][b]Bans[/b][/color]*\n[list]\n[*] [url=http://hackforums.net/member.php?action=profile&uid=431105][color=#000000][b]Tɦɛ Gʀiɱ[/b][/color][/url] was banned. \n[/list]\n\n[color=white][b]Vacations[/b][/color]*\n[list]\n[*] [url=http://hackforums.net/member.php?action=profile&uid=952566][color=#000000][b]Armada[/b][/color][/url] has taken a vacation. \n[*] [url=http://hackforums.net/member.php?action=profile&uid=2682887][color=#000000][b]Mr. Robot[/b][/color][/url] has taken a vacation. \n[/list]\n\n[color=white][b]Closures[/b][/color]\n[list]\n[*] [url=http://hackforums.net/member.php?action=profile&uid=891268][color=#383838][b]OnTheFly[/b][/color][/url] was closed.\n[*] [url=http://hackforums.net/member.php?action=profile&uid=2776397][color=#383838][b]Young Thug[/b][/color][/url] was closed. \n[*] [url=http://hackforums.net/member.php?action=profile&uid=1164025][color=#383838][b]King of Diamonds[/b][/color][/url] was closed. \n[*] [url=http://hackforums.net/member.php?action=profile&uid=96732][color=#383838][b]exod[/b][/color][/url] was closed. \n[*] [url=http://hackforums.net/member.php?action=profile&uid=3181877][color=#383838][b]Rox[/b][/color][/url] was closed.\n[/list]\n\n[color=white][b]Rep Kills[/b][/color]\n[list]\n[*] [url=http://hackforums.net/member.php?action=profile&uid=3080905][color=white][b]Vizi[/b][/color][/url] was Rep Killed. \n[*] [url=http://hackforums.net/member.php?action=profile&uid=891268][color=#383838][b]OnTheFly[/b][/color][/url] was Rep Killed. \n[*] [url=http://hackforums.net/member.php?action=profile&uid=2029278][color=#00AAFF][b]Barrier.[/b][/color][/url] was Rep Killed. \n[*] [url=http://hackforums.net/member.php?action=profile&uid=2776397][color=#383838][b]Young Thug[/b][/color][/url] was Rep Killed. \n[*] [url=http://hackforums.net/member.php?action=profile&uid=1164025][color=#383838][b]King of Diamonds[/b][/color][/url] was Rep Killed. \n[*] [url=http://hackforums.net/member.php?action=profile&uid=96732][color=#383838][b]exod[/b][/color][/url] was Rep Killed. \n[/list]\n\n[color=white][b]Awards[/b][/color]\n[list]\n[*] No notable awards were reported this week!\n[/list]\n\n[size=x-small]* = prior to the Friday of release![/size]\n\n[color=transparent]       [/color]\n\n[align=center][img]http://www.hackforums.news/assets/v3/NotableThreads.png[/img][/align]\n\n[list][b][color=white][u]Announcement Threads[/u][/color][/b]\n[list]\n\nNo announcement threads this week.[/list][/list]\n\n[list][b][color=white][u]Informational Threads[/u][/color][/b]\n[list]\n\n[url=http://hackforums.net/showthread.php?tid=5415687][b][Tutorial] Creating a pentesting network in Virtualbox (megaguide)[/b][/url] - [url=http://hackforums.net/member.php?action=profile&uid=3041169][b][color=#99FF00]Reece Morgan[/color][/b][/url]\nThanks to Reece Morgan you now have a chance to learn how to create a pentesting network using VirtualBox. A lengthy guide which includes pictures and steps to get you started.\n\n[url=http://hackforums.net/showthread.php?tid=5400626][b][Tutorial] Fast,free and easy way to check for system infections of FUD malware[/b][/url] - [url=http://hackforums.net/member.php?action=profile&uid=898091][b][color=#FFFFFF]Fộrcəd[/color][/b][/url]\nQuick and easy method to check if your system is infected. It is always good to check on things yourself so that in the future you can get rid of infections if it ever occurs again.\n\n[url=http://hackforums.net/showthread.php?tid=5416812][b][TUTORIAL] How To Play Splitscreen With 2 Monitors[/b][/url] - [url=http://hackforums.net/member.php?action=profile&uid=1485583][b][color=#00AAFF]Dangerous Beef[/color][/b][/url]\nA small little guide on how to setup your monitors (if you have more than one) to play a splitscreen game with a friend.[/list][/list]\n\n[list][b][color=white][u]Entertaining Threads[/u][/color][/b]\n[list]\n\n[url=http://hackforums.net/showthread.php?tid=5410860][b]Top 5 TV Series?[/b][/url] - [url=http://hackforums.net/member.php?action=profile&uid=3251346][b][color=#FFFFFF]TheDoctor541[/color][/b][/url]\nPost your top five shows here. Maybe you will find more things to watch that interest you thanks to the lists of others!\n\n[url=http://hackforums.net/showthread.php?tid=5416362][b]Does money make you happy?[/b][/url] - [url=http://hackforums.net/member.php?action=profile&uid=3224097][b][color=#FFFFFF]Iceh[/color][/b][/url]\nHow important is money to you? Does it make you happy? If not, what does? If it does, why?\n\n[url=http://hackforums.net/showthread.php?tid=5413134][b]Someone has a big ass botnet | Brian Krebs offline | OVH hit with 1156Gbps[/b][/url] - [url=http://hackforums.net/member.php?action=profile&uid=931348][b][color=#FFFFFF]Djehuty[/color][/b][/url]\nSomeone with a huge botnet has hit the infamous Brian Krebs off the internet. Read more about it and discuss it here!\n\n[url=http://hackforums.net/showthread.php?tid=5412861][b]Take the challenge now. See how fast you can type. Post results![/b][/url] - [url=http://hackforums.net/member.php?action=profile&uid=3085259][b][color=#99FF00]Akhenaten[/color][/b][/url]\nThink you are the fastest typer on the forum? Take a test here and post your results to show off your skills.[/list][/list]\n\n[list][b][color=white][u]Member Feedback Threads[/u][/color][/b]\n[list]\nNo feedback threads this week.[/list][/list]\n\n[list][b][color=white][u]Contests and Giveaways[/u][/color][/b]\n[list]\n\n[url=http://hackforums.net/showthread.php?tid=5412171][b][The Order] L33T Giveaway / $18[/b][/url] - [url=http://hackforums.net/member.php?action=profile&uid=2739889][b][color=#FFFFFF]heartthrob[/color][/b][/url]\nNormal members, if you would like the chance to win L33t membership come to this thread. Now is your chance to get the L33t upgrade you desire!\n\n[url=http://hackforums.net/showthread.php?tid=5415872][b][NON-UPGRADED MEMBERS] L33t OR 3p1c Giveaway - [1/5][/b][/url] - [url=http://hackforums.net/member.php?action=profile&uid=2920830][b][color=#FFFFFF]Confound[/color][/b][/url]\nVery generous giveaway from the user Confound. Members looking to win a L33t or 3P1C upgrade can do so by entering this contest!\n\n[url=http://hackforums.net/showthread.php?tid=5415609][b]$10 BTC GIVEAWAY [upgraded only][/b][/url] - [url=http://hackforums.net/member.php?action=profile&uid=2943145][b][color=#99FF00]OMEGAAA[/color][/b][/url]\nThis contest ends on the 30 of this month. Quickly enter before it ends for the chance to win some money. Everyone loves money, right?\n\n[url=http://hackforums.net/showthread.php?tid=5410712][b][ VeloCityMods & FamousHater ] Brony Award/$75 BTC Giveaway[/b][/url] - [url=http://hackforums.net/member.php?action=profile&uid=3106226][b][color=#FFFFFF]VeloCityMods[/color][/b][/url]\nEven if you are not a Brony it is still a cool award to have. Right?! If this award is not something you want you also have the chance to win $75 instead.\n\n[url=http://hackforums.net/showthread.php?tid=5411724][b][The Order] Brony Award Giveaway | $100 AWARD![/b][/url] - [url=http://hackforums.net/member.php?action=profile&uid=1165241][b][color=#FFFFFF]Krave[/color][/b][/url]\nThe Order has recently spammed the giveaways sections with a bunch of different giveaways. One of those is hosted by the leader himself, Krave. The award is worth $100 which may be a lot for some. For the chance to win a Brony award, post here.[/list][/list]\n\n[list][b][color=white][u]Miscellaneous[/u][/color][/b]\n[list]\n\n[url=http://hackforums.net/showthread.php?tid=5412687][b]Just made pancakes [with picture][/b][/url] - [url=http://hackforums.net/member.php?action=profile&uid=1999047][b][color=#FFFFFF]Vitani[/color][/b][/url]\nCome look at the pancakes that fellow Writer, Vitani made!\n\n[url=http://hackforums.net/showthread.php?tid=4902796][b][The Order] Clearing up Misconceptions about Homosexuality + Answers from LGBT[/b][/url] - [url=http://hackforums.net/member.php?action=profile&uid=988432][b][color=#FFFFFF]Nevieth[/color][/b][/url]\nThe user Nevieth has updated his help desk to discuss anything LGBT and give members support if needed.\n\n[url=http://hackforums.net/showthread.php?tid=5412918][b]My African fish tank (African themed environment)[/b][/url] - [url=http://hackforums.net/member.php?action=profile&uid=2494088][b][color=#00AAFF]Muddy Waters[/color][/b][/url]\nMuddy Waters is showing off his pretty cool fish collection. Muddy owns an awesome tank with some cool looking fish![/list][/list]\n\n[color=transparent]       [/color]\n\n[hr]\n\n[align=center][img]http://hackforums.news/assets/v3/Interview/310.png[/img][/align]\n\n[align=center][color=white][size=large][font=Monotype Corsiva]Interview[/font][/size][/color] [color=white][size=large][font=Monotype Corsiva]-[/font][/size][/color] [size=large][font=Monotype Corsiva][url=http://hackforums.net/member.php?action=profile&uid=981500]Premortal:[/url][/font][/size][spoiler=][align=left]\n[url=http://www.hackforums.net/member.php?action=profile&uid=1148878][color=#FF69B4][b]Clique:[/b][/color][/url] Hi there and welcome to this weeks edition of the HF news. Any shout outs before begin?\n[url=http://hackforums.net/member.php?action=profile&uid=981500][color=white][b]Premortal:[/b][/color][/url] Hello Clique, thanks for having me! I don't think I have any shout outs in mind.\n\n[url=http://www.hackforums.net/member.php?action=profile&uid=1148878][color=#FF69B4][b]Clique:[/b][/color][/url]  Sounds good. So what do you do outside of HF? Are you in school?\n[url=http://hackforums.net/member.php?action=profile&uid=981500][color=white][b]Premortal:[/b][/color][/url] I'm on and off with school, but mainly I work a pretty easy blue collar job and make strides to improve my writing. I spend entirely too much time consuming different types of media, but I enjoy it and it gives me a chance to see the fruits that come from the labors of others. It's like its own sort of motivation for me.\n\n[url=http://www.hackforums.net/member.php?action=profile&uid=1148878][color=#FF69B4][b]Clique:[/b][/color][/url] Since you've been on HF for quite some time -- do you still like it here?\n[url=http://hackforums.net/member.php?action=profile&uid=981500][color=white][b]Premortal:[/b][/color][/url] Oh I definitely like it. Just with the sort of subject matter that HF revolves around you can always be sure that there's something interesting going on. The multiple senses of community that are ingrained in this site really help make it a fun place to have discussions and meet people. So many different kinds of people are attracted to the idea of hacking and all the different things it entails, be it money or notoriety or even knowledge. Hack Forums ends up being this great cocktail of both information and entertainment.\n\n[url=http://www.hackforums.net/member.php?action=profile&uid=1148878][color=#FF69B4][b]Clique:[/b][/color][/url] Do you go on any other boards or is HF your only one? I for one love browsing reddit.\n[url=http://hackforums.net/member.php?action=profile&uid=981500][color=white][b]Premortal:[/b][/color][/url] I'm a big fan of Reddit myself, but you don't see nearly as much there in the way of individuality throughout the different subreddits. Outside of your karma and your post history there really isn't much going on with the average Reddit user's profile. I like having an avatar and a signature to create an image for myself on top of the threads and replies that I make. Having usergroups, reputation points, and awards goes even further with that personalization by showing who a person may be affiliated with, what they do, what they're known for, and overall just what kind of member that they are. I like have so many different platforms available to help define myself for others.\n\n[url=http://www.hackforums.net/member.php?action=profile&uid=1148878][color=#FF69B4][b]Clique:[/b][/color][/url] Agreed. What got you into HF? Was it from a friend or just found out by yourself?\n[url=http://hackforums.net/member.php?action=profile&uid=981500][color=white][b]Premortal:[/b][/color][/url]It being so long ago and having been so subtle of an event I ended up forgetting all of the specific details, but I remember when googling how to do certain computer related activities I'd see threads from Hack Forums show up in the results, and since it didn't let you actually read the threads unless you made an account I figured I'd be fine with making one. I really wasn't all that active for my first three to six months on the site, but it became a part of my regular schedule to check on and post things on the site, and I guess things sorta snowballed. I gained a feel for the site and the community and consciously decided that I enjoyed being here, which isn't something I can say for every site I've ever joined on a whim.\n\n[url=http://www.hackforums.net/member.php?action=profile&uid=1148878][color=#FF69B4][b]Clique:[/b][/color][/url] Glad you stuck around. Unrelated question, but are you going to see the new Snowden movie? What movies have you seen recently?\n[url=http://hackforums.net/member.php?action=profile&uid=981500][color=white][b]Premortal:[/b][/color][/url] I'm most definitely going to need to see it sometime soon. I never got around to seeing Citizenfour, but I heard that it was really well done and I'd imagine Joseph Gordon-Levitt does a solid Snowden. Some movies that I've seen recently are Hell and High Water, which was released this year, and the original Predator, which came out in the late 80's. Hell or High Water I really, really enjoyed and would like to see nominated for some Academy awards, just because it's able to very effectively balance having a generally slow-burning plot while still keeping the audiences attention with well placed scenes of action and tension. The original Predator movie is great, probably one of my favorite cheesy action movies from the 80's. It's definitely got some cheesiness going on, but the plot and acting are sincere enough to grab the audience while still going through the fairly basic plot with enough suspense to stay interesting.\n\n[url=http://www.hackforums.net/member.php?action=profile&uid=1148878][color=#FF69B4][b]Clique:[/b][/color][/url] Just saw Snowden, loved it. Predator was great, a classic in my opinion. What's your opinion on groups nowdays?\n[url=http://hackforums.net/member.php?action=profile&uid=981500][color=white][b]Premortal:[/b][/color][/url] I don't think they're nearly as big a part of the forum as they used to be, at least outside of the marketplace anyway. With how much groups sell for, I can't imagine anyone being able to purchase one without having at least some intentions of making their money back. When they were cheaper (or free) it wasn't nearly as bad, but most group purchases are made with financial gain in mind rather than setting good standards for different parts of the forum. \n\nOrganization for groups could probably be a lot better as well. It always annoys me when I see someone asking for ideas for a group's subject, because if it's something you aren't personally passionate about it isn't something you're going to be able to make strides with in terms of productivity and community involvement, because eventually you'll just lose interest and either find some other subject you don't care about or sell the group.\n\nLounge groups are okay, but I really think that it ends up wasting the potential that's present in a lot of groups. I always do my lounging in Team Speak and Discord, and it used to be that Tinychat was the place to go for lounging. A lot of us don't really see the need for that type of stuff inside of a private group subforum, and I know for myself even in lounge threads in otherwise non-lounge groups I'm not usually too active because I don't see the point. \n\nGroup activity starts from the top, and if there's a group that's inactive it's gonna be because the leaders and owners aren't active themselves. But if you take the Red Lions for example, nokia2mon2 may not be very active at all, but he grants enough liberty to !!**Alone Vampire**!! and the rest of the Red Lions that we can initiate projects and activity as we please, leading us to have a very active and objective-based subforum. Of course, this relies on the leaders recruiting members who are both active and very sincere in their desire to help Hack Forums, and I think that meticulousness when recruiting is key when it comes to a group's success. When it comes down to it, a group is nothing more than just a collective of members, and the words and actions of those members outside of the subforum define for the rest of Hack Forums just what exactly a group's about.\n\n[url=http://www.hackforums.net/member.php?action=profile&uid=1148878][color=#FF69B4][b]Clique:[/b][/color][/url] You think HF would be as active as it is now if groups didn't exist?\n[url=http://hackforums.net/member.php?action=profile&uid=981500][color=white][b]Premortal:[/b][/color][/url] Oh for sure, but I don't think there would be nearly as much of a community-type feel to the site. Having a marketplace and a bunch of good informational threads are what I see as mainly drawing people to the site, but groups give members a reason to keep coming back to the site and staying active. Groups are definitely a big part of HF's success as a social hub.\n\n[url=http://www.hackforums.net/member.php?action=profile&uid=1148878][color=#FF69B4][b]Clique:[/b][/color][/url] Thanks for your time. Any other thoughts before we finish this interview?\n[url=http://hackforums.net/member.php?action=profile&uid=981500][color=white][b]Premortal:[/b][/color][/url] I think that's about it! Thanks for interviewing me, it's always fun sharing my thoughts and opinions with the HF community. Check out the Red Lions Discord server in my signature if you ever feel like chatting.\n[/align]\n[/align]\n[/spoiler]\n\n[hr]\n\n[color=transparent]       [/color][/size][/font]",
      "subject": "Hack Forums News // Edition 310"
    },
    {
      "pid": "52579898",
      "uid": "561239",
      "dateline": "1474988750",
      "message": "[font=Trebuchet MS][size=1][color=transparent]       [/color]\r\n\r\n[align=center][img]http://hackforums.news/assets/v3/2-303.png[/img][/align]\r\n\r\n[color=transparent]       [/color]\r\n\r\n[align=center][img]http://hackforums.news/assets/v3/SupportHFN.png[/img][/align]\r\n\r\n[align=center]We publish the HF News every week yet we have aged members who don't even know we exist! Wear any of the signatures listed below to support us and spread the word about HF News, HF Wiki, and Writers altogether. \r\n\r\n[color=white][spoiler=[b]Support Signatures[/b]]\r\n\r\n[color=white][b]-1-[/b][/color]\r\n[url=http://bitly.com/1FnhESq][img]http://i.imgur.com/pdoOihY.png[/img][/url]\r\n[code][align=center][url=http://bitly.com/1FnhESq][img]http://i.imgur.com/pdoOihY.png[/img][/url][/align][/code]\r\n\r\n[color=white][b]-2-[/b][/color]\r\n[url=http://bitly.com/1FnhESq][img]https://i.imgur.com/VTs6K6A.gif[/img][/url]\r\n[code][align=center][url=http://bitly.com/1FnhESq][img]https://i.imgur.com/VTs6K6A.gif[/img][/url][/align][/code]\r\n\r\n[color=white][b]-3-[/b][/color]\r\n[url=http://bitly.com/1FnhESq][img]https://i.imgur.com/hkLhk6f.gif[/img][/url]\r\n[code][align=center][url=http://bitly.com/1FnhESq][img]https://i.imgur.com/hkLhk6f.gif[/img][/url][/align][/code]\r\n\r\n[color=white][b]-4-[/b][/color]\r\n[url=http://bitly.com/1FnhESq][img]https://i.imgur.com/ceUBlwQ.gif[/img][/url]\r\n[code][align=center][url=http://bitly.com/1FnhESq][img]https://i.imgur.com/ceUBlwQ.gif[/img][/url][/align][/code]\r\n\r\n[color=white][b]-5-[/b][/color]\r\n[url=http://bitly.com/1FnhESq][img]https://i.imgur.com/54dbXHH.gif[/img][/url]\r\n[code][align=center][url=http://bitly.com/1FnhESq][img]http://i.imgur.com/pdoOihY.png[/img][/url][/align][/code]\r\n\r\n[color=white][b]-6-[/b][/color]\r\n[url=http://bitly.com/1FnhESq][img]https://i.imgur.com/oowqdqM.gif[/img][/url]\r\n[code][align=center][url=http://bitly.com/1FnhESq][img]https://i.imgur.com/oowqdqM.gif[/img][/url][/align][/code]\r\n\r\n[color=white][b]-7-[/b][/color]\r\n[url=http://bitly.com/1FnhESq][img]https://i.imgur.com/KssvPNL.gif[/img][/url]\r\n[code][align=center][url=http://bitly.com/1FnhESq][img]https://i.imgur.com/KssvPNL.gif[/img][/url][/align][/code]\r\n[/spoiler][/color][/align]\r\n\r\n[color=transparent]       [/color]\r\n\r\n[align=center][img]http://hackforums.news/assets/v3/Memo.png[/img][/align]\r\n\r\n[b][color=white]Another Week, Another Edition[/color][/b]\r\nThanks for reading the HF News this week, see you next week! \r\n\r\n[color=transparent]   [/color]\r\n\r\n[align=center][img]http://www.hackforums.news/assets/v3/WorldNews.png[/img][/align]\r\n\r\n[b][color=white]Indian Court Rules Copyright is not a Divine Right[/color][/b]\r\nPublishers were thwarted in their attempt to stop Delhi University from issuing photocopies of textbooks. The Delhi high court said that “copyright is not a divine right,” and that the university may continue to issue photocopies of major textbooks without penalty. In India, education is exempted from copyright infringement under Section 52 of the Copyright Act. The lawsuit from the publishers began in 2012, and was finally ended on September 16, 2016 with a 94-page order in favor of the defendant. [i][size=x-small][url=http://timesofindia.indiatimes.com/city/delhi/Copyright-is-not-a-divine-right-Delhi-HC/articleshow/54372014.cms] >>Source[/url][/size][/i]\r\n\r\n[b][color=white]Penalties Increased if Caught Using Mobile Phone While Driving[/color][/b]\r\nUnder new measures, people in the UK that are caught using their phone twice while driving will now lose their license. The UK penalty system is point-based, and those caught using their phone earn an automatic six points. Six points is halfway towards a standard driver losing their license for six months. For new drivers, they are only allowed six points total, which means they will lose their license after being caught once.  On top of the point penalty, any offending driver will face a fine of at least £200. Research has shown that those who are using their phone while driving can have up to a 50% slower reaction time. The new measures are intended to discourage dangerous behavior on the roadways.[i][size=x-small][url=http://www.independent.co.uk/news/get-caught-on-the-phone-twice-while-driving-and-you-will-lose-your-licence-a7312221.html] >>Source[/url][/size][/i]\r\n\r\n[b][color=white]Sweden Will Offer Tax Breaks for Repairs[/color][/b]\r\nIn an attempt to combat wasteful tendencies, Sweden is cutting the VAT on repairs of all kinds. Currently, the VAT sits at 25% for repairs, but Sweden’s Socialist Democrat and Green party will submit proposals to reduce the VAT to 12%. Furthermore, citizens will be allowed to claim back half of the value of labor costs for repairs from their income tax. It is believed that in addition to the conservation this will generate, the repair industry of Sweden will be economically stimulated.[i][size=x-small][url=https://www.theguardian.com/world/2016/sep/19/waste-not-want-not-sweden-tax-breaks-repairs] >>Source[/url][/size][/i]\r\n\r\n[color=transparent]    [/color]\r\n\r\n[align=center][img]http://hackforums.news/assets/v3/TechNews/Gladly.png[/img][/align]\r\n\r\n[align=left][url=https://it.slashdot.org/story/16/09/22/095255/yahoo-confirms-massive-data-breach-hundreds-of-millions-of-users-impacted-updated][b]Yahoo Suffers Massive Data Breach[/b][/url]\r\nWhat may be the largest data breach of all time, massive email client Yahoo has had their database of users breached. Yahoo has confirmed the breach, stating that over 500 million usernames, MD5 hashed passwords, and possibly addresses were stolen. The breach may have occurred as early as 2014, with Yahoo keeping it a secret, advising users who haven't changed their passwords and security information since 2014 to do so. This all occurs in the midst of Yahoo being sold to Verizon, with Yahoo shareholders terrified that this could lower the company's value.\r\n\r\n[url=https://motherboard.vice.com/read/valve-bans-game-publisher-after-it-sues-players-that-gave-it-bad-steam-reviews][b]Valve Bans Game Publisher that Sued Users Giving Bad Steam Reviews[/b][/url]\r\nAfter receiving plenty of negative publicity in 2014 for suing a game reviewer for $10 million after a bad review, video game publisher Digital Homicide is back at it again, suing hundreds of users who left them bad Steam reviews on multiple games. In total, the publisher is suing users for a whopping $18 million, just over negative reviews. This resulted in plenty of outcry from the community - so much so that Valve, the company that owns Steam, to remove Digital Homicide's entire library of games from Steam.\r\n\r\n[url=http://www.mirror.co.uk/tech/reddit-brings-down-north-koreas-8881736][b]North Korea's DNS Leaks, Revealing All of Country's Websites[/b][/url]\r\nThe nation of North Korea is one shrouded in mystery and poverty, with outsiders getting very rare and infrequent chances to get a glimpse of the country. A rare look into North Korea's internet occurred this week, thanks to a slip up by a North Korean official. The mistake turned North Korea's closed internet public for a short while, revealing a measly 28 .nk domains in the country. Along with this information, GitHub users used the temporarily public information to find that for the 25 million person population, there were about 1,000 IPs total. This is not surprising though, as internet is a very rare privilege, mostly for North Korea's high class, wealthy, or researchers. Some of the websites are more typical than others, such as Cooks.org.kp, a cooking and recipe website on the North Korean domain. While someone at North Korea has fixed the DNS leak, websites received so much foreign traffic while they were public that they went offline.\r\n[/align]\r\n\r\n[color=transparent]      [/color]\r\n\r\n[align=center][img]http://hackforums.news/assets/v3/GamingNews.png[/img][/align]\r\n[b][url=http://www.gamespot.com/articles/hideo-kojima-reveals-new-death-stranding-details/1100-6443517/][color=white]New Death Stranding Details Emerge[/color][/url][/b]\r\nWe received a substantial amount of new information about Hideo Kojima's mysterious upcoming game, Death Stranding. Speaking at Sony Playstation's pre-Tokyo Game Show keynote presentation, Kojima revealed the elusive meaning behind the game's title and logo. Kojima stated that the game's logo isn't dripping ink or liquid, but are actually cords. He further explained that the theme of the game with be exploring how people are connected by strands which explains the game's unusual title -- Death Stranding. Kojima didn't stop there. He revealed that the game will fall into the action genre and that it will be open world with a \"degree of freedom.\" Death Stranding will also feature online elements. Kojima spoke of his wish to give gamers a way to be connected via these \"strands,\" or elements that are different to the usual multiplayer teams. Kojima also recently teased the possibility of a female protagonist to star alongside Norman Reedus in a recent [url=https://twitter.com/KojiPro2015_EN/status/777374076138430464]tweet[/url]. According to the tweet, there could be a heroine featured in the game, but it looks like that possibility is still up in the air, and the studio is still looking for potential actresses to take on the role. Given Kojima’s love for strong and iconic female characters in the Metal Gear series, it is likely that we’ll see a heroine in Death Stranding as well. A release date hasn't been discussed but it is rumored to be release in 2018.\r\n\r\n[b][url=http://www.gamespot.com/articles/pokemon-go-battle-mode-teased/1100-6443739/][color=white]Pokemon Go: PVP[/color][/url][/b]\r\nFollowing the release of the Buddy system update, Pokemon Company CEO, Tsunekazu Ishihara, told the Wall Street Journal that Niantic Lab is taking its time in releasing new features for the game so that it doesn't overwhelm newcomers. A player-versus-player battle system is on the company's map. \"Battling is a category that we do best at Pokemon, after all,\" Ishihara stated. \"It's important to really carefully consider any feature that may increase the difficulty and raise the barrier to entry for more casual users.\" Ishihara didn't directly comment on their plans in introducing a trading system, but it was mentioned in the same report. In July, Niantic Labs CEO John Hanke confirmed that a trading system would be on its way soon enough, but there was no information shared regarding how it would work. Similarly, we don't know much about the battle system that Niantic is planning to release. \"The multiplayer aspect is still something we're exploring, we're still trying to figure out what's the best way to do that,\" Bhargava said. \"So far we've learned that multiplayer battles are a lot of fun. When two people from different teams show up at a rival gym, if they collaborate and both have their Pokemon deployed to battle at the same time, they can take down a stronger gym faster.\" \"But we're trying our best to rethink what the experience should be; what that real-world Pokemon experience should be like. Obviously we're learning from Ingress, but it's going to be a pretty different game. We have a vision for Pokemon, we're gonna execute on it, but we're gonna learn based on what the community reaction is.\" Niantic has a lot in store for us and it appears that they are seriously considering what the community thinks to ensure future updates are a success. Which features are you most looking forward to? Let us know!\r\n\r\n[b][url=http://www.gamespot.com/articles/square-enix-plans-to-make-premium-mobile-games-a-p/1100-6443892/][color=white]Square Enix Utilizing Mobile Gaming Platform[/color][/url][/b]\r\nSquare Enix today released its 2016 annual report to investors, which outlines three key initiatives it plans to pursue going forward--one of which is premium mobile games. Square Enix has been releasing numerous premium games on smart devices for years. In 2006, the publisher was already speaking about the growth it saw in mobile gaming and expressed a lot of interest in pursuing them. In the past few years, they've released plenty of original games like Lara Croft Go, Mobius Final Fantasy, and they've even released ports of existing titles like Final Fantasy 9 and Adventures of Mana. Mobile games have been cited as one of the reasons for their surge in profits in past earnings reports. \"Currently, the global market for smart device games is dominated by F2P (free to play) games, and the market for premium games that players pay to purchase is practically nonexistent,\" he said in the annual report. \"However, our group has for some time been offering premium games for smart devices, including brand-new titles. When viewed across the group, these offerings represent a considerable volume of earnings.\" Matsuda then turned his attention to handheld games, essentially explaining what's been apparent for years: mobile games are increasingly taking their place. As a result, Square Enix believes it makes sense to develop handheld games for mobile platforms in addition to handhelds. Square Enix has a lot in store and perhaps they'll revolutionize mobile gaming since they appear to be devote to turning out original games for mobile platforms.\r\n\r\n[color=transparent]   [/color][/size][/font]",
      "subject": "*"
    },
    {
      "pid": "52581072",
      "uid": "561239",
      "dateline": "1474997681",
      "message": "[font=Trebuchet MS][size=1][color=transparent]       [/color]\n\n[align=center][img]http://www.hackforums.news/assets/v3/3-301.png[/img][/align]\n\n[color=transparent]       [/color]\n\n[align=center][img]http://www.hackforums.news/assets/v3/Spotlight.png[/img][/align]\n\n[align=center][url=http://hackforums.net/showthread.php?tid=5415585][b][color=white]Rob Zombie - Illustration[/color][/b][/url]\n[img]http://hackforums.news/assets/v3/Spotlight/310-1.png[/img]\nBy [b][url=http://hackforums.net/member.php?action=profile&uid=2991977][color=#99FF00]Nuance[/color][/url][/b][/align]\n\n[align=center][url=http://hackforums.net/showthread.php?tid=5406431][b][color=white]Misty River[/color][/b][/url]\n[img]http://hackforums.news/assets/v3/Spotlight/310-2.png[/img]\nBy [b][url=http://hackforums.net/member.php?action=profile&uid=1420194][color=#00AAFF]CyberneticTitan[/color][/url][/b][/align]\n\n[color=transparent]   [/color]\n\n[align=center][img]http://www.hackforums.news/assets/v3/Trends.png[/img][/align]\n\n[url=http://www.cnn.com/2016/09/25/us/mlb-pitcher-jose-fernandez-dead/index.html][color=#FFFFFF][b]MLB Pitcher Jose Fernandez Dead[/b][/color][/url]\nThe 24-year-old Miami Marlins pitcher known as José Fernández was killed in the morning of September 25. Fernández and two other individuals were found at the scene of the accident, dead, at the entrance of Miami Harbor. The two other victims were also in their 20s, but their names are not being released to the public at this time. There appeared to be no lead that drugs or alcohol were used that night, but cannot be confirmed until the autopsy reports are completed.\n\n[url=http://golfweek.com/2016/09/25/arnold-palmer-passes-away-at-87/][color=#FFFFFF][b]Arnold Palmer Dies at age 87[/b][/color][/url]\nThe golf king, Arnold Palmer, died on the afternoon of September 25 due to heart complications. Palmer was 87 years old and a golf icon to say the least. Palmer was a seven-time major winner and truly did bring people's attention to the game of golf. Alastair Johnson, CEO of Arnold Palmer Enterprises, said that Palmer was admitted to the hospital for cardiovascular work, but weakened later in the days thus leading him to his passing.\n\n[url=http://www.eonline.com/news/797669/brad-pitt-angelina-jolie-break-up-everything-we-ve-learned-in-the-span-of-a-week][color=#FFFFFF][b]Brad Pitt and Angelina Jolie Divorce[/b][/color][/url]\nThe last couple we would have ever expected to break up, has. On September 19, Angelina Jolie officially filed for divorce. She is seeking full-time custody of the children while only giving Brad visitation rights. Angelina's manager, Geyer Kosinski, says, \"Angelina will always do what's in the best interest of taking care of her family. She appreciates everyone's understanding of their need for privacy at this time. Shortly after Angelina's statement, Brad releases his own statement, \"I am very saddened by this, but what matters most now is the wellbeing of our kids. I kindly ask the press to give them the space they deserve during this challenging time.\" Best of luck to both of them.\n\n[color=transparent]         [/color]\n\n[align=center][img]http://www.hackforums.news/assets/v3/Comics/Vitani.png[/img]\n\n[b][size=x-large]|1|[/size][/b][sp=]\n[img]http://i.imgur.com/q5xFUsz.png[/img][/sp]\n\n[b][size=x-large]|2|[/size][/b][sp=]\n[img]http://i.imgur.com/rRV4bGO.png[/img][/sp]\n\n[b][size=x-large]|3|[/size][/b][sp=]\n[img]http://i.imgur.com/vByt2Z7.png[/img][/sp]\n\n[b][size=x-large]|4|[/size][/b][sp=]\n[img]http://i.imgur.com/WwuJZ3P.png[/img][/sp]\n\n[b][size=x-large]|5|[/size][/b][sp=]\n[img]http://i.imgur.com/DXiXTVD.png[/img][/sp][/align]\n\n[color=transparent]         [/color]\n\n[align=center][img]http://hackforums.news/assets/v3/Credits.png[/img][/align]\n[align=center][sp=View Team][align=left]\n\n[list][*][color=white][b][u]Scholars[/u][/b][/color]\n[list]\n[*][url=http://hackforums.net/member.php?action=profile&uid=2504443]Queenie[/url][/list][/list]\n\n[list][*][color=white][b][u]Journalists[/u][/b][/color]\n[list][*]Headlines\n[list][*][url=http://hackforums.net/member.php?action=profile&uid=121196]Natha[/url][/list][/list]\n[list][*]User News\n[list][*][url=http://hackforums.net/member.php?action=profile&uid=525019]illuminati▲[/url][/list][/list]\n[list][*]Notable Threads\n[list][*][url=http://hackforums.net/member.php?action=profile&uid=XXXXXX]OPEN[/url][/list][/list]\n[list][*]Interviewers\n[list][*][url=http://hackforums.net/member.php?action=profile&uid=2214473].Sinister[/url][color=#98FB98]*[/color], [url=http://hackforums.net/member.php?action=profile&uid=952566]Armada[/url], & [url=http://hackforums.net/member.php?action=profile&uid=1148878]Clique[/url], [url=http://hackforums.net/member.php?action=profile&uid=1957866]Enterpriser[/url][/list][/list]\n[list][*]Group News\n[list][*][url=http://hackforums.net/member.php?action=profile&uid=XXXXXX]OPEN[/url][/list][/list]\n[list][*]Site News\n[list][*][url=http://hackforums.net/member.php?action=profile&uid=2577525]Hash G.[/url][/list][/list]\n[list][*]Hacking News\n[list][*][url=http://hackforums.net/member.php?action=profile&uid=1422600]Fox™[/url][/list][/list]\n[list][*]Gaming News\n[list][*][url=http://hackforums.net/member.php?action=profile&uid=2364291]Buffy Summers[/url][/list][/list]\n[list][*]Tech News\n[list][*][url=http://hackforums.net/member.php?action=profile&uid=1356937]Angеl[/url] & [url=http://hackforums.net/member.php?action=profile&uid=1730460]Gladly[/url][/list][/list]\n[list][*]World News\n[list][*][url=http://hackforums.net/member.php?action=profile&uid=2110841]Night Fury[/url][/list][/list]\n[list][*]Science News\n[list][*][url=http://hackforums.net/member.php?action=profile&uid=XXXXXX]OPEN[/url][/list][/list]\n[list][*]Spotlight\n[list][*][url=http://hackforums.net/member.php?action=profile&uid=561239]iHydra[/url][/list][/list]\n[list][*]Trends\n[list][*][url=http://hackforums.net/member.php?action=profile&uid=712376]Joey[/url][/list][/list]\n[list][*]Comics\n[list][*][url=http://hackforums.net/member.php?action=profile&uid=610356]Wires[/url] & [url=http://hackforums.net/member.php?action=profile&uid=1999047]Vitani[/url][/list][/list]\n[list][*]On-Call Team\n[list][*][url=http://hackforums.net/member.php?action=profile&uid=610356]Wires[/url][color=#98FB98]*[/color], [url=http://hackforums.net/member.php?action=profile&uid=1221196]King Cin[/url], [url=http://hackforums.net/member.php?action=profile&uid=85546]Odus[/url], [url=http://hackforums.net/member.php?action=profile&uid=692131]Ariana[/url], [url=http://hackforums.net/member.php?action=profile&uid=2776397]Young Thug[/url], [url=http://hackforums.net/member.php?action=profile&uid=1999047]Vitani[/url][/list][/list][/list]\n\n[list][*][color=white][b][u]Support[/u][/b][/color]\n[list][*]Edition Mover\n[list][*][url=http://hackforums.net/member.php?action=profile&uid=992020]King of Hearts[/url][/list][/list]\n[list][*]Backup Publisher\n[list][*][url=http://hackforums.net/member.php?action=profile&uid=1093501]Roger Waters[/url][/list][/list][/list]\n\n[color=#FFFFFF][i]*Those with an asterisk are supervisors of that team.[/i][/color]\n\n[/align][/sp][/align]\n[color=transparent]         [/color][/size][/font]",
      "subject": "*"
    }
  ]
}