{
  "posts": [
    {
      "pid": "57270822",
      "uid": "561239",
      "dateline": "1530082234",
      "message": "[font=Trebuchet MS][size=medium][color=transparent]       [/color]\n\n[align=center][IMG]https://hackforums.news/assets/v3/397.png[/IMG][/align]\n\n[color=transparent]       [/color]\n\n[align=center][url=https://hackforums.net/member.php?action=profile&uid=561239][img]https://hackforums.news/assets/v3/Headlines/iHydra.png[/img][/url][/align]\n\n[b][color=white]GDPR Discussion[/color][/b]\nOmniscient recently pushed out new policies so Hack Forums can be compliant with the newly launched GDPR. A thread was created as many started to question a few agreement points. If you do have any questions or wanted to read through the pages, head on over to that thread to read more.[i][size=x-small][url=https://hackforums.net/showthread.php?tid=5853729] >>Source[/url][/size][/i]\n\n[b][color=white]4 New Donation Awards[/color][/b]\nFour new donation awards have been added, each going for $25 and are giftable. All four are cryptocurrency related: Qtum, Waves, PivX, and Lisk.[i][size=x-small][url=https://hackforums.net/showthread.php?tid=5854004] >>Source[/url][/size][/i]\n\n[b][color=white]What's Prestige?[/color][/b]\nPrestige is no longer a thing, that's what. A points system is in the works which will have a more meaningful use for the community unlike Prestige. Omniscient believes Prestige was dated and no longer of use to the forum.[i][size=x-small][url=https://hackforums.net/showthread.php?tid=5853746] >>Source[/url][/size][/i]\n\n[b][color=white]Contracts Required for Currency Exchange[/color][/b]\nIt is now a bannable offense to refuse/not use Contracts system when doing currency exchange. Currency Exchange threads must contain the Contracts MyCode. Read the thread for specific details.[i][size=x-small][url=https://hackforums.net/showthread.php?tid=5852705] >>Source[/url][/size][/i]\n\n[color=transparent]       [/color]\n\n[align=center][img]https://i.imgur.com/wYi4ilf.jpg[/img][/align] \n [color=white][b]Site Statistics[/b][/color] \n [list][*][sp=[b]Total[/b]] \n [list][*][u]Posts:[/u] 36,975,607 ([color=#32CD32]+0.11%[/color][color=white][b]|[/color][/b][color=#32CD32]+41,583[/color]) \n [*][u]Threads:[/u] 3,632,856 ([color=#32CD32]+0.11%[/color][color=white][b]|[/color][/b][color=#32CD32]+4,084[/color]) \n [*][u]Members:[/u] 657,206 ([color=#32CD32]+1.12%[/color][color=white][b]|[/color][/b][color=#32CD32]+7,310[/color])[/list][/sp][/list] \n [list][*][sp=[b]Average[/b]] \n [list][*][u]Daily Posts:[/u] 8,353.84 ([color=#FF0000]-0.11%[/color][color=white][b]|[/color][/b][color=#FF0000]-9.5[/color]) \n [*][u]Daily Threads:[/u] 820.77 ([color=#FF0000]-0.11%[/color][color=white][b]|[/color][/b][color=#FF0000]-0.93[/color]) \n [*][u]Daily New Members:[/u] 148.48 ([color=#32CD32]+0.9%[/color][color=white][b]|[/color][/b][color=#32CD32]+1.32[/color]) \n [*][u]Posts Per Member:[/u] 56.26 ([color=#FF0000]-1%[/color][color=white][b]|[/color][/b][color=#FF0000]-0.57[/color]) \n [*][u]Replies Per Thread:[/u] 5.53 ([color=#FF0000]-0.9%[/color][color=white][b]|[/color][/b][color=#FF0000]-0.05[/color])[/list][/sp][/list] \n [b][color=white]Ban Statistics[/color][/b] \n [list][*][sp=[b]Last Weeks Bans[/b]] \n [list][*][u]Staff Bans:[/u] 0 \n [list][*][i]... Change from Last Edition:[/i] [color=#FF0000]-42[/color][/list][/list] \n [list][*][u]Vacation Bans:[/u] 0 \n [list][*][i]... Change from Last Edition:[/i] [color=#FF0000]-18[/color][/list][/list] \n [list][*][u]Combined Bans:[/u] 0 \n [list][*][i]... Change from Last Edition:[/i] [color=#FF0000]-60[/color][/list][/list][/sp][/list] \n [color=white][b]Forum Counts[/b][/color] \n [list][*][sp=[b]Tab Counts[/b]] \n [list][*][b]Notable Sections[/b] \n [list][*][u][url=http://hackforums.net/forumdisplay.php?fid=25][b]Lounge[/b][/url] Threads:[/u] 227,189 ([color=#32CD32]+0.21%[/color][color=white][b]|[/color][/b][color=#32CD32]+469[/color]) \n [*][u][url=http://hackforums.net/forumdisplay.php?fid=25][b]Lounge[/b][/url] Posts:[/u] 3,652,659 ([color=#32CD32]+0.19%[/color][color=white][b]|[/color][/b][color=#32CD32]+6,963[/color]) \n [*][u][url=http://hackforums.net/forumdisplay.php?fid=2][b]RANF[/b][/url] Threads:[/u] 71,706 ([color=#32CD32]+0.15%[/color][color=white][b]|[/color][/b][color=#32CD32]+105[/color]) \n [*][u][url=http://hackforums.net/forumdisplay.php?fid=2][b]RANF[/b][/url] Posts:[/u] 1,134,098 ([color=#32CD32]+0.14%[/color][color=white][b]|[/color][/b][color=#32CD32]+1,552[/color])[/list][/list] \n [list][*][b]Common[/b] \n [list][*][u]Threads:[/u] 550,419 ([color=#32CD32]+0.16%[/color][color=white][b]|[/color][/b][color=#32CD32]+863[/color]) \n [*][u]Posts:[/u] 8,574,386 ([color=#32CD32]+0.15%[/color][color=white][b]|[/color][/b][color=#32CD32]+12,959[/color])[/list][/list] \n [list][*][b]Hack[/b] \n [list][*][u]Threads:[/u] 728,224 ([color=#32CD32]+0.07%[/color][color=white][b]|[/color][/b][color=#32CD32]+540[/color]) \n [*][u]Posts:[/u] 6,335,478 ([color=#32CD32]+0.12%[/color][color=white][b]|[/color][/b][color=#32CD32]+7,519[/color]) [/list][/list] \n [list][*][b]Tech[/b] \n [list][*][u]Threads:[/u] 217,826 ([color=#32CD32]+0.04%[/color][color=white][b]|[/color][/b][color=#32CD32]+83[/color]) \n [*][u]Posts:[/u] 1,816,740 ([color=#32CD32]+0.02%[/color][color=white][b]|[/color][/b][color=#32CD32]+351[/color])[/list][/list] \n [list][*][b]Code[/b] \n [list][*][u]Threads:[/u] 174,765 ([color=#32CD32]+0.05%[/color][color=white][b]|[/color][/b][color=#32CD32]+81[/color]) \n [*][u]Posts:[/u] 1,485,833 ([color=#32CD32]+0.03%[/color][color=white][b]|[/color][/b][color=#32CD32]+469[/color])[/list][/list] \n [list][*][b]Game[/b] \n [list][*][u]Threads:[/u] 467,096 ([color=#32CD32]+0.03%[/color][color=white][b]|[/color][/b][color=#32CD32]+122[/color]) \n [*][u]Posts:[/u] 4,811,602 ([color=#32CD32]+0.02%[/color][color=white][b]|[/color][/b][color=#32CD32]+731[/color])[/list][/list] \n [list][*][b]Groups[/b] \n [list][*][u]Threads:[/u] 8,308 ([color=#32CD32]+0.1%[/color][color=white][b]|[/color][/b][color=#32CD32]+8[/color]) \n [*][u]Posts:[/u] 356,265 ([color=#32CD32]+0.07%[/color][color=white][b]|[/color][/b][color=#32CD32]+245[/color])[/list][/list] \n [list][*][b]Web[/b] \n [list][*][u]Threads:[/u] 88,483 ([color=#32CD32]+0.06%[/color][color=white][b]|[/color][/b][color=#32CD32]+56[/color]) \n [*][u]Posts:[/u] 635,326 ([color=#32CD32]+0.04%[/color][color=white][b]|[/color][/b][color=#32CD32]+244[/color])[/list][/list] \n [list][*][b]GFX[/b] \n [list][*][u]Threads:[/u] 138,950 ([color=#32CD32]+0.03%[/color][color=white][b]|[/color][/b][color=#32CD32]+35[/color]) \n [*][u]Posts:[/u] 1,034,586 ([color=#32CD32]+0.02%[/color][color=white][b]|[/color][/b][color=#32CD32]+240[/color])[/list][/list] \n [list][*][b]Market[/b] \n [list][*][u]Threads:[/u] 1,103,603 ([color=#32CD32]+0.14%[/color][color=white][b]|[/color][/b][color=#32CD32]+1,531[/color]) \n [*][u]Posts:[/u] 9,825,159 ([color=#32CD32]+0.09%[/color][color=white][b]|[/color][/b][color=#32CD32]+8,906[/color])[/list][/list] \n [list][*][b]Money[/b] \n [list][*][u]Threads:[/u] 138,528 ([color=#32CD32]+0.11%[/color][color=white][b]|[/color][/b][color=#32CD32]+159[/color]) \n [*][u]Posts:[/u] 1,722,639 ([color=#32CD32]+0.35%[/color][color=white][b]|[/color][/b][color=#32CD32]+6,034[/color])[/list][/list] \n [/sp][/list]\n\n[color=transparent]       [/color]\n\n[align=center][url=https://hackforums.net/member.php?action=profile&uid=3444267][img]https://cybercustom.com/uploads/hfnews/cylow_group.png[/img][/url][/align]\n\n[b][color=white]Groups For Sale[/color][/b]\n[list]\n[*][url=https://hackforums.net/member.php?action=profile&uid=2292899][b]Divined[/b][/url] is selling [url=https://hackforums.net/showthread.php?tid=5824217]a group.[/url]\n[/list]\n\n[b][color=white]Leadership Changes[/color][/b]\n\n[list]\n[*][url=https://hackforums.net/member.php?action=profile&uid= 3020519][b][color=white]sword[/color][/b][/url] is now a leader of Heroes.\n[/list]\n\n[b][color=white]Group Recruitments[/color][/b]\n[list]\n[*][url=https://hackforums.net/showthread.php?tid=5826205][b]Appraisers - Rolling Recruitment[/b][/url]\n[*][url=https://hackforums.net/showthread.php?tid=5785470][b]Famous - Social Media[/b][/url]\n[*][url=https://hackforums.net/showthread.php?tid=5843047][b]Legends -  Hacking Recruitment[/b][/url]\n[*][url=https://hackforums.net/showthread.php?tid=5831943][b]Samaritans - General Recruitment[/b][/url]\n[*][url=https://hackforums.net/showthread.php?tid=5825672][b]Samaritans - Magazine Recruitment[/b][/url]\n[*][url=https://hackforums.net/showthread.php?tid=5778655][b]SheepGang - Gaming Recruitment[/b][/url]\n[*][url=https://hackforums.net/showthread.php?tid=5819193][b]Skill -  General Gaming Recruitment[/b][/url]\n[*][url=https://hackforums.net/showthread.php?tid=5819753][b]Skill - RuneScape Sector Recruitment[/b][/url]\n[*][url=https://hackforums.net/showthread.php?tid=5789158][b]Sui Generis - GFX Recruitment[/b][/url]\n[*][url=https://hackforums.net/showthread.php?tid=5788019][b]Sui Generis - Literature Recruitment[/b][/url]\n[*][url=https://hackforums.net/showthread.php?tid=5789838][b]Sui Generis - Media Recruitment[/b][/url]\n[*][url=https://hackforums.net/showthread.php?tid=5787983][b]Sui Generis - Music Recruitment[/b][/url]\n[*][url=https://hackforums.net/showthread.php?tid=5833285][b]Terminal - General Recruitment[/b][/url]\n[/list]\n\n[b][color=white]Group Threads[/color][/b]\n[list]\n[*][url=https://hackforums.net/showthread.php?tid=5787149][b]Appraisers Information[/b][/url]\n[*][url=https://hackforums.net/showthread.php?tid=5649245][b]Influence Information[/b][/url]\n[*][url=https://hackforums.net/showthread.php?tid=5267722][b]Legends Information[/b][/url]\n[*][url=https://hackforums.net/showthread.php?tid=5807501][b]Samaritans Information[/b][/url]\n[*][url=https://hackforums.net/showthread.php?tid=5779017][b]Sui Generis Information[/b][/url]\n[*][url=https://hackforums.net/showthread.php?tid=5814889][b]Unity Roadmap[/b][/url]\n[size=small] *As of the Friday prior to release. [/size]\n[/list]\n\n\n[color=transparent]       [/color]\n\n[align=center][url=https://hackforums.net/member.php?action=profile&uid=1034038][img]https://i.imgur.com/QV3JZ5c.png[/img][/url][/align]\n\n[color=white][b]User News[/b][/color]\n[list]\n[*][url=https://hackforums.net/member.php?action=profile&uid=2947999][color=#ffffff][b]Views[/b][/color][/url] has purchased 1,000 reputation.\n[/list]\n\n[color=white][b]Bans[size=x-small]*[/size][/b][/color]\n[list]\n[*][url=https://hackforums.net/member.php?action=profile&uid=2439716][color=#000][b]Vyrez.[/b][/color][/url] has received a week-long ban for post-bump deleting. \n[*][url=https://hackforums.net/member.php?action=profile&uid=2947999][color=#000][b]Views[/b][/color][/url] received a week-long ban, which turned into a six-month ban for rep abuse, then ultimately got it reversed. [i]*Now Closed*[/i]\n[/list]\n\n[color=white][b]Vacations[size=x-small]*[/size][/b][/color]\n[list]\n[*]Unavailable due to disabled Bans page.\n[/list]\n\n[color=white][b]Closures[/b][/color]\n[list]\n[*][url=https://hackforums.net/member.php?action=profile&uid=2947999][color=#666][b]Views[/b][/color][/url] is now closed in regards to this [url=https://hackforums.net/showthread.php?tid=5852472]thread[/url]. Omniscient's [url=https://hackforums.net/showthread.php?tid=5852472&pid=57268386#pid57268386]response[/url].\n[/list]\n\n[color=white][b]Awards[/b][/color]\n[list]\n[*]No notable awards provided this week!\n[/list]\n\n[align=left][size=x-small][color=white][b]*[/b][/color]As of the Sunday prior to release.[/size][/align]\n\n[color=transparent]       [/color]\n\n[align=center][url=https://hackforums.net/member.php?action=profile&uid=1034038][img]https://i.imgur.com/Fd16M6F.png[/img][/url][/align]\n\n[color=#FFFFFF][b]Announcements[/b][/color]\n[list]\n[*][url=https://hackforums.net/showthread.php?tid=5853746][color=#FFFFFF]What was Prestige?[/color][/url] - [url=https://hackforums.net/member.php?action=profile&uid=1][color=#9999FF][b]Omniscient[/b][/color][/url]\nOmniscient announces the removal of the Prestige feature. \n\n[*][url=https://hackforums.net/showthread.php?tid=5854004][color=#FFFFFF]Donation Awards Added[/color][/url] - [url=https://hackforums.net/member.php?action=profile&uid=1][color=#9999FF][b]Omniscient[/b][/color][/url]\nOmniscient has added four new awards available for purchase, which can also be gifted. \n\n[*][url=https://hackforums.net/showthread.php?tid=5853729][color=#FFFFFF]GDPR Discussion[/color][/url] - [url=https://hackforums.net/member.php?action=profile&uid=1][color=#9999FF][b]Omniscient[/b][/color][/url]\nIn-depth explanation for the recent GDPR law implementations. \n\n[*][url=https://hackforums.net/showthread.php?tid=5847086&pid=57246416#pid57246416][color=#FFFFFF]Marketplace Suite and Contracts[/color][/url] - [url=https://hackforums.net/member.php?action=profile&uid=175033][color=#9999FF][b]Xerotic[/b][/color][/url]\nA post by Xerotic sampling the new addition of \"Contracted Customers\" on paid stickies. \n[/list]\n\n[color=#FFFFFF][b]Entertaining Threads[/b][/color]\n[list]\n[*][url=https://hackforums.net/showthread.php?tid=5851969][color=#FFFFFF]The Diary of a Homeless Hacker[/color][/url] - [url=https://hackforums.net/member.php?action=profile&uid=952566][color=#FFFFFF][b]Armada[/b][/color][/url]\nAn online entry and description of Armada's current situation as a homeless hacker. \n[/list]\n\n[color=#FFFFFF][b]Contests & Giveaways[/b][/color]\n[list]\n[*][url=https://hackforums.net/showthread.php?tid=5853627][color=#FFFFFF][June] Official Auction: Xerotic Bot DNA Award[/color][/url] - [url=https://hackforums.net/member.php?action=profile&uid=175033][color=#9999FF][b]Xerotic[/b][/color][/url]\nXerotic's June hosting of his official award. \n\n[*][url=https://hackforums.net/showthread.php?tid=5852271][color=#FFFFFF]$250 BTC giveaway[/color][/url] - [url=https://hackforums.net/member.php?action=profile&uid=3836233][color=#FFCC00][b]P4DDY[/b][/color][/url]\n$250 BTC giveaway hosted by P4DDY. \n[/list]\n\n[color=transparent]       [/color][/size][/font]",
      "subject": "Hack Forums News // Edition 397"
    },
    {
      "pid": "57270989",
      "uid": "561239",
      "dateline": "1530087295",
      "message": "[font=Trebuchet MS][size=medium][color=transparent]       [/color]\r\n\r\n[align=center][img]http://hackforums.news/assets/v3/2-303.png[/img][/align]\r\n\r\n[color=transparent]       [/color]\r\n\r\n[align=center][img]http://hackforums.news/assets/v3/SupportHFN.png[/img][/align]\r\n\r\n[align=center]We publish the HF News every week yet we have aged members who don't even know we exist! Wear any of the signatures listed below to support us and spread the word about HF News, HF Wiki, and Writers altogether. \r\n\r\n[color=white][spoiler=[b]Support Signatures[/b]]\r\n\r\n[color=white][b]-1-[/b][/color]\r\n[url=http://bitly.com/1FnhESq][img]http://i.imgur.com/pdoOihY.png[/img][/url]\r\n[code][align=center][url=http://bitly.com/1FnhESq][img]http://i.imgur.com/pdoOihY.png[/img][/url][/align][/code]\r\n\r\n[color=white][b]-2-[/b][/color]\r\n[url=http://bitly.com/1FnhESq][img]https://i.imgur.com/VTs6K6A.gif[/img][/url]\r\n[code][align=center][url=http://bitly.com/1FnhESq][img]https://i.imgur.com/VTs6K6A.gif[/img][/url][/align][/code]\r\n\r\n[color=white][b]-3-[/b][/color]\r\n[url=http://bitly.com/1FnhESq][img]https://i.imgur.com/hkLhk6f.gif[/img][/url]\r\n[code][align=center][url=http://bitly.com/1FnhESq][img]https://i.imgur.com/hkLhk6f.gif[/img][/url][/align][/code]\r\n\r\n[color=white][b]-4-[/b][/color]\r\n[url=http://bitly.com/1FnhESq][img]https://i.imgur.com/ceUBlwQ.gif[/img][/url]\r\n[code][align=center][url=http://bitly.com/1FnhESq][img]https://i.imgur.com/ceUBlwQ.gif[/img][/url][/align][/code]\r\n\r\n[color=white][b]-5-[/b][/color]\r\n[url=http://bitly.com/1FnhESq][img]https://i.imgur.com/54dbXHH.gif[/img][/url]\r\n[code][align=center][url=http://bitly.com/1FnhESq][img]http://i.imgur.com/pdoOihY.png[/img][/url][/align][/code]\r\n\r\n[color=white][b]-6-[/b][/color]\r\n[url=http://bitly.com/1FnhESq][img]https://i.imgur.com/oowqdqM.gif[/img][/url]\r\n[code][align=center][url=http://bitly.com/1FnhESq][img]https://i.imgur.com/oowqdqM.gif[/img][/url][/align][/code]\r\n\r\n[color=white][b]-7-[/b][/color]\r\n[url=http://bitly.com/1FnhESq][img]https://i.imgur.com/KssvPNL.gif[/img][/url]\r\n[code][align=center][url=http://bitly.com/1FnhESq][img]https://i.imgur.com/KssvPNL.gif[/img][/url][/align][/code]\r\n[/spoiler][/color][/align]\r\n\r\n[color=transparent]   [/color]\r\n\r\n[align=center][url=https://hackforums.net/member.php?action=profile&uid=3322334][img]https://i.imgur.com/H5MRIbN.png[/img][/url][/align]\r\n\r\n[b][color=white]US Greenhouse Emissions are Higher Than we Thought[/color][/b] \r\nA new study pegs the United States' greenhouse gas emissions at nearly 60% higher than the Environmental Protection Agency stated. This study points out that previously thought \"clean\" gasses may not be as good for the planet as we think. This study, conducted by the Environmental Defence Fund, also estimates the leakage of  US pipelines at almost double that of the EPA's percentage. Steven Hamburg, a co-author of the paper, says \"this is by far the most comprehensive body of research of its kind.\" This study certainly seems to warrant further research into our prolonged effects on the environment.  [i][size=x-small][url=https://www.usatoday.com/story/news/nation/2018/06/21/emissions-greenhouse-gas-methane-higher-than-epa-thinks/722391002/]>>Source[/url][/size][/i]\r\n\r\n[b][color=white]I Learned it From you![/color][/b] \r\nEmotional eating is one of the larger problems in our society. A recent study published in Pediatric Obesity suggests that there is almost zero correlation between it and genetics. Instead, the study claims that young ones learn it by watching how their parents eat, or do not, during stressful situations. “Experiencing stress and negative emotions can have a different effect on appetite for different people. Some crave their favourite snack, whereas others lose their desire to eat altogether when feeling stressed or sad. This study supports our previous findings suggesting that children’s emotional over- and under-eating are mostly influenced by environmental factors completely shared by twin pairs and that genes are largely unimportant for emotional overeating in childhood.\" says Dr. Moritz Herle. [i][size=x-small][url=http://www.ucl.ac.uk/news/news-articles/0618/180618_emotional_eating]>>Source[/url][/size][/i]\r\n\r\n[color=transparent]   [/color]\r\n\r\n[align=center][img]https://i.imgur.com/lv4d7BY.png[/img][/align]\r\n\r\n[b][color=white]2020 Tokyo Games to be fully powered by renewable energy, organizers say[/color][/b] \r\nDuring the 2020 Tokyo Games, the organizing committee aims to power the games using renewable energy, in an effort to pave the path of awareness for a more sustainable society. “All electricity used at all venues will be derived entirely from renewable energy sources, in order to promote decarbonization.” Additionally, the committee in charge intends to use leasing services for their power sources, that way “99 percent of the good procured for the games will be reused or recycled.” The renewable energy aims to target the powering of the “athletes’ village, the international broadcasting center and the main press center.” The renewable energy will be provided by power companies and the installation of solar panels. Though the price is a factor, the main intent of this decision is to cut back on fossil fuels and promote other forms of energy production. The vast majority of products will be rented and leased, however necessary purchases will be made. In regard to plastic bottles and leftover food, the committee aims to recycle at least 65% of all generated waste. The committee plans to execute another project involving the residents, “in addition to an ongoing initiative to create games medals out of metals collected from used mobile phones and other equipment.” The strive for such a [i]clean[/i] Games is to promote sustainability among the public and is ‘crucial to pass it on as a legacy,” “an official said.” [i][size=x-small][url=https://www.japantimes.co.jp/news/2018/06/22/national/2020-tokyo-games-fully-powered-renewable-energy-organizers-say/#.Wy2H-tn92Um]>>Source[/url][/size][/i]\r\n\r\n[b][color=white]North Korea 'total denuclearization' started; officials see no new moves[/color][/b] \r\nOn Thursday, 21 May 2018, President Trump released an official statement, where, in certainty, he provided a glimpse of progress inside of the North Korea-United States nuclear deal. He stated that they began progress, further explaining that the country “was blowing up four of its big test sites and that a process of ‘total denuclearization has already started,’ however, officials said that no such evidence has made itself apparent. At the Cabinet meeting, he further stated that ‘They’ve stopped the sending of missiles, including ballistic missiles. They’re destroying their engine site. They’re blowing it up. They’ve already blown up one of their big test sites, in fact it’s actually four of their big test sites.” Upon discussion, Cabinet members were unclear of which North Korean test sites President Trump was referring to, and according U.S. officials who are “familiar with current intelligence on North Korea’s nuclear and missile test sites,” there has been no evidence or movements to undergo the disabling or destruction of any sites since the meeting between the two leaders on 12 June. After continued discussions, the same official spoke on potential targets that Trump could have been referring to. Earlier in May, North Korea was said to have planned on destroying “tunnels at the Punggye-ri nuclear test site and the dismantling of a medium-range ballistic missile test stand at Iha-ri,” although it is not with certainty that this is what the president spoke in reference to.   [i][size=x-small][url=https://www.reuters.com/article/us-northkorea-usa-sites/trump-north-korea-total-denuclearization-started-officials-see-no-new-moves-idUSKBN1JH2QX?utm_source=reddit.com]>>Source[/url][/size][/i]\r\n\r\n[color=transparent]   [/color][/size][/font]",
      "subject": "RE: Hack Forums News // Edition 397"
    }
  ]
}