{
  "posts": [
    {
      "pid": "53975638",
      "uid": "561239",
      "dateline": "1485901299",
      "message": "[font=Trebuchet MS][size=1][color=transparent]       [/color]\r\n\r\n[align=center][IMG]http://hackforums.news/assets/v3/328.png[/IMG][/align]\r\n\r\n[color=transparent]       [/color]\r\n\r\n[align=center][img]http://www.hackforums.news/assets/v3/Headlines/iHydra.png[/img][/align]\r\n\r\n[b][color=white]Omniscient Threatened[/color][/b]\r\n[url=https://hackforums.net/member.php?action=profile&uid=2529154][b][color=#454545]Tommy[/color][/b][/url] has contacted [url=https://hackforums.net/member.php?action=profile&uid=1][b][color=#FF66FF]Omniscient[/color][/b][/url] through the forum to let him know he is coming after him and his family. No thread was created by [url=https://hackforums.net/member.php?action=profile&uid=1][b][color=#FF66FF]Omniscient[/color][/b][/url] however he did tweet out a screenshot of Tommy's post.[i][size=x-small][url=https://twitter.com/HackForumsNet/status/825129861786202113] >>Source[/url][/size][/i]\r\n\r\n[color=transparent]       [/color]\r\n\r\n[align=center][url=https://hackforums.net/member.php?action=profile&uid=692131][img]https://hackforums.news/assets/v3/SiteNews/Tsundere.png[/img][/url][/align][color=white][b]Site Statistics[/b][/color] \r\n[list][*][sp=[b]Total[/b]] \r\n[list][*][u]Posts:[/u] 53,967,130 ( [color=#32CD32]+0.17%[/color] ) \r\n[*][u]Threads:[/u] 3,741,715 ( [color=#32CD32]+0.23%[/color] ) \r\n[*][u]Members:[/u] 3,448,715 ( [color=#32CD32]+0.38%[/color] )[/list][/sp][/list] \r\n[list][*][sp=[b]Average[/b]] \r\n[list][*][u]Daily Posts:[/u] 13,757.27 ( [color=#FF0000]-0.07%[/color] ) \r\n[*][u]Daily Threads:[/u] 953.84 ( [color=#FF0000]-0.002%[/color] ) \r\n[*][u]Daily New Members:[/u] 879.14 ( [color=#32CD32]+0.14%[/color] ) \r\n[*][u]Posts Per Member:[/u] 15.65 ( [color=#FF0000]-0.19%[/color] ) \r\n[*][u]Replies Per Thread:[/u] 13.42 ( [color=#FF0000]-0.07%[/color] )[/list][/sp][/list] \r\n  [b][color=white]Ban Statistics[/color][/b] \r\n[list][*][sp=[b]Last Weeks Bans[/b]] \r\n[list][*][u]Staff Bans:[/u] 119 \r\n[list][*][i]... Change from Last Edition:[/i] [color=#32CD32]+14[/color][/list][/list] \r\n[list][*][u]Vacation Bans:[/u] 14 \r\n[list][*][i]... Change from Last Edition:[/i] [color=#FF0000]-2[/color][/list][/list] \r\n[list][*][u]Combined Bans:[/u] 133 \r\n[list][*][i]... Change from Last Edition:[/i] [color=#32CD32]+12[/color][/list][/list][/sp][/list] \r\n[color=white][b]Forum Counts[/b][/color] \r\n[list][*][sp=[b]Tab Counts[/b]] \r\n[list][*][b]Notable Sections[/b] \r\n[list][*][u][url=https://hackforums.net/forumdisplay.php?fid=25][b]Lounge[/b][/url] Threads:[/u] 525,072 ( [color=#32CD32]+0.17%[/color] ) \r\n[*][u][url=https://hackforums.net/forumdisplay.php?fid=25][b]Lounge[/b][/url] Posts:[/u] 7,831,566 ( [color=#32CD32]+0.16%[/color] ) \r\n[*][u][url=https://hackforums.net/forumdisplay.php?fid=2][b]RANF[/b][/url] Threads:[/u] 68,247 ( [color=#32CD32]+0.12%[/color] ) \r\n[*][u][url=https://hackforums.net/forumdisplay.php?fid=2][b]RANF[/b][/url] Posts:[/u] 1,089,274 ( [color=#32CD32]+0.09%[/color] )[/list][/list] \r\n[list][*][b]Common[/b] \r\n[list][*][u]Threads:[/u] 817,395 ( [color=#32CD32]+0.2%[/color] ) \r\n[*][u]Posts:[/u] 12,285,506 ( [color=#32CD32]+0.2%[/color] )[/list][/list] \r\n[list][*][b]Hack[/b] \r\n[list][*][u]Threads:[/u] 688,108 ( [color=#32CD32]+0.16%[/color] ) \r\n[*][u]Posts:[/u] 6,005,934 ( [color=#32CD32]+0.15%[/color] )[/list][/list] \r\n[list][*][b]Tech[/b] \r\n[list][*][u]Threads:[/u] 208,164 ( [color=#32CD32]+0.14%[/color] ) \r\n[*][u]Posts:[/u] 1,744,625 ( [color=#32CD32]+0.13%[/color] )[/list][/list] \r\n[list][*][b]Code[/b] \r\n[list][*][u]Threads:[/u] 168,108 ( [color=#32CD32]+0.12%[/color] )\r\n[*][u]Posts:[/u] 1,438,010 ( [color=#32CD32]+0.09%[/color] )[/list][/list] \r\n[list][*][b]Game[/b] \r\n[list][*][u]Threads:[/u] 454,916 ( [color=#32CD32]+0.09%[/color] ) \r\n[*][u]Posts:[/u] 4,704,836 ( [color=#32CD32]+0.07%[/color] )[/list][/list] \r\n[list][*][b]Groups[/b] \r\n[list][*][u]Threads:[/u] 7,657 ( [color=#32CD32]+0.34%[/color] ) \r\n[*][u]Posts:[/u] 332,387 ( [color=#32CD32]+0.23%[/color] )[/list][/list] \r\n[list][*][b]Web[/b] \r\n[list][*][u]Threads:[/u] 83,670 ( [color=#32CD32]+0.19%[/color] ) \r\n[*][u]Posts:[/u] 605,023 ( [color=#FF0000]-12.82%[/color] )[/list][/list] \r\n[list][*][b]GFX[/b] \r\n[list][*][u]Threads:[/u] 134,785 ( [color=#32CD32]+0.09%[/color] ) \r\n[*][u]Posts:[/u] 1,007,028 ( [color=#32CD32]+0.08%[/color] )[/list][/list] \r\n[list][*][b]Market[/b] \r\n[list][*][u]Threads:[/u] 1,006,462 ( [color=#32CD32]+0.21%[/color] ) \r\n[*][u]Posts:[/u] 8,918,295 ( [color=#32CD32]+0.26%[/color] ) [/list][/list] \r\n[list][*][b]Money[/b] \r\n[list][*][u]Threads:[/u] 141,812 ( [color=#32CD32]+0.19%[/color] ) \r\n[*][u]Posts:[/u] 1,852,253 ( [color=#32CD32]+0.15%[/color] )[/list][/list][/list] \r\n[/sp] \r\n [color=white][b]Membership Counts[/b][/color] \r\n [list][*][sp=[b]Groups[/b]] \r\n[list][*][b]Baka[/b] \r\n[list][*]88 Members ( [color=#32CD32]+5[/color] )[/list] \r\n[*][b]Dawn[/b] \r\n[list][*]19 Members ( [color=#FFD700]~[/color] )[/list] \r\n[*][b]Echo[/b] \r\n[list][*]34 Members ( [color=#FFD700]~[/color] )[/list] \r\n[*][b]Eclipse[/b] \r\n[list][*]13 Members ( [color=#FFD700]~[/color] )[/list] \r\n[*][b]Aequitas[/b] \r\n[list][*]8 Members ( [color=#32CD32]+3[/color] )[/list] \r\n[*][b]Escrow[/b] \r\n[list][*]2 Members ( [color=#FFD700]~[/color] )[/list] \r\n[*][b]Fusion[/b] \r\n[list][*]351 Members ( [color=#32CD32]+9[/color] )[/list] \r\n[*][b]Illuminati[/b] \r\n[list][*]18 Members ( [color=#32CD32]+3[/color] )[/list] \r\n[*][b]Legends[/b] \r\n[list][*]21 Members ( [color=#FFD700]~[/color] )[/list] \r\n[*][b]The Marketers[/b] \r\n[list][*]8 Members ( [color=#FFD700]~[/color] )[/list] \r\n[*][b]Notorious[/b] \r\n[list][*]44 Members ( [color=#FF0000]-2[/color] )[/list] \r\n[*][b]Red Lions[/b] \r\n[list][*]16 Members ( [color=#32CD32]+1[/color] )[/list] \r\n[*][b]Equilibrium[/b] \r\n[list][*]28 Members ( [color=#FFD700]~[/color] )[/list] \r\n[*][b]Royalty[/b] \r\n[list][*]48 Members ( [color=#32CD32]+5[/color] )[/list] \r\n[*][b]Torque[/b] \r\n[list][*]70 Members ( [color=#FFD700]~[/color] )[/list] \r\n[*][b]The Brotherhood[/b] \r\n[list][*]24 Members ( [color=#FFD700]~[/color] )[/list][/list]\r\n[list][*][b]The Order[/b] \r\n[list][*]40 Members ( [color=#FF0000]-6[/color] )[/list][/list][/sp][/list]\r\n\r\n[color=transparent]       [/color]\r\n\r\n[align=center][img]https://i.imgur.com/UfteD6z.png[/img][/align]\r\n\r\n[b][color=white]Leadership Changes[/color][/b]\r\n\r\n[list][*][url=https://hackforums.net/member.php?action=profile&uid=2875087]exploit.c[/url] is stepping down as a leader in Royalty. [url=https://hackforums.net/showthread.php?tid=5533513][size=xx-small]>>read here[/size][/url].\r\n[*][url=https://hackforums.net/member.php?action=profile&uid=2951661]Thermal the Prophet[/url] is now a leader in Royalty. [url=https://hackforums.net/showthread.php?tid=5536761][size=xx-small]>>read here[/size][/url].\r\n[/list]\r\n\r\n[b][color=white]Group Programs[/color][/b]\r\n\r\n[list][*][url=https://hackforums.net/showthread.php?tid=5486883][b][Official Group] Notorious - Apprenticeship Program | Join and Learn![/b][/url]\r\n[*][url=https://hackforums.net/showthread.php?tid=5484911][b]Join Royalty - [ Ethical Hacking STUDENT PROGRAM ] - Official Group[/b][/url][/list]\r\n\r\n[b][color=white]Group Recruitments[/color][/b]\r\n[list]\r\n[*][url=https://hackforums.net/showthread.php?tid=5536761][b][Official] Royalty[/b][/url]\r\n[*][url=https://hackforums.net/showthread.php?tid=5536119][b]Marketers [Official Group] - Now recruiting[/b][/url]\r\n[*][url=https://hackforums.net/showthread.php?tid=5535851][b][Official Group] Torque - Recruitment Thread[/b][/url]\r\n[*][url=https://hackforums.net/showthread.php?tid=5435261][b]Echo | Lounge recruitment[/b][/url]\r\n[*][url=https://hackforums.net/showthread.php?tid=5489201][b]Equilibrium[/b][/url]\r\n[*][url=https://hackforums.net/showthread.php?tid=5476730][b]Hack Forums Wiki -- Recruiting Journalists [L33T/UB3R][/b][/url]\r\n[*][url=https://hackforums.net/showthread.php?tid=5494167][b]Hack Forums Wiki -- Recruiting Editors [L33T/UB3R][/b][/url]\r\n[*][url=https://hackforums.net/showthread.php?tid=5376863][b]Illuminati | Novus Ordo Seclorum | Apply[/b][/url]\r\n[*][url=https://hackforums.net/showthread.php?tid=5506129][b][Official] Notorious - Recruitment #2[/b][/url]\r\n[*][url=https://hackforums.net/showthread.php?tid=5525114][b]Think Into Royalty [Official Group] #4[/b][/url]\r\n[*][url=https://hackforums.net/showthread.php?tid=5453346][b][Official Group Royalty] Recruitment to New Sector! Ethical Hacking[/b][/url]\r\n[*][url=https://hackforums.net/showthread.php?tid=5509213][b]The Brotherhood - Recruitment Thread [Offical Group][/b][/url]\r\n[/list]\r\n\r\n[b][color=white]Informational and Buy-in Threads[/color][/b]\r\n\r\n[list]\r\n[*][url=https://hackforums.net/showthread.php?tid=5531813][b]Marketers - General Information[/b][/url]\r\n[*][url=https://hackforums.net/showthread.php?tid=5499945][b][OFFICIAL] Dawn Sector --- Dawn Innuendo || Information Thread[/b][/url]\r\n[*][url=https://hackforums.net/showthread.php?tid=5475631][b][Final Nightmare Lifetime Membership - $100 BTC (1 year guaranteed membership)[/b][/url]\r\n[*][url=https://hackforums.net/showthread.php?tid=5485890][b][SALE] Sector in Nightmare (Mod Privileges) Reduced price $250 (OPEN TO OFFERS)[/b][/url]\r\n[*][url=https://hackforums.net/showthread.php?tid=5508614][b][Official] The Brotherhood is Back || Information Thread[/b][/url]\r\n[*][url=https://hackforums.net/showthread.php?tid=5521856][b][Official Group] The Order | Purchase A Group Spot[/b][/url]\r\n[/list]\r\n\r\n[b][color=white]Groups for sale[/color][/b]\r\n\r\n[list][*][url=https://hackforums.net/showthread.php?tid=5505005][b][OFFICIAL GROUP] Fusion for Sale[/b][/url][/list]\r\n[align=left][size=x-small][color=white][b]*[/b][/color]As of the Friday prior to release.[/size][/align]\r\n\r\n[color=transparent]       [/color]\r\n\r\n[align=center][img]https://hackforums.news/assets/v3/NotableThreads/Tsundere.png[/img][/align]\r\n\r\n[list][b][color=white][u]Announcement Threads[/u][/color][/b]\r\n[list]\r\n\r\nNo announcements were made this week![/list][/list]\r\n\r\n[list][b][color=white][u]Informational Threads[/u][/color][/b]\r\n[list]\r\n\r\n[url=https://hackforums.net/showthread.php?tid=5535456][b][Notorious] Ultimate DNS Guide for beginners[/b][/url] - [url=https://hackforums.net/member.php?action=profile&uid=1201211][b][color=#EFEFEF]ƅzrK[/color][/b][/url]\r\nIf you are new to using Remote Administration Tools, then you may have some questions concerning Domain Name System or DNS for short. ƅzrK has created a very helpful thread to assist beginners and get them going in the world of RATing.\r\n\r\n[url=https://hackforums.net/showthread.php?tid=5534413][b]HunTeR's Helpdesk | Supplements and Steroids | All things bodybuilding[/b][/url] - [url=https://hackforums.net/member.php?action=profile&uid=2202059][b][color=#EFEFEF]Hu‎‎n‎TeR‎[/color][/b][/url]\r\nHunTeR's has created a thread to assist those looking to gain some knowledge in supplements and taking steroids. Anything bodybuilding can be asked in this thread.\r\n\r\n[url=https://hackforums.net/showthread.php?tid=5533413][b]How To Massively Increase Your Testosterone Naturally[/b][/url] - [url=https://hackforums.net/member.php?action=profile&uid=3203007][b][color=#EFEFEF]Anonymality[/color][/b][/url]\r\nThe contents of this thread contain information that will help users increase their testosterone naturally. A very informative guide on how to get you on the right path.\r\n\r\n[url=https://hackforums.net/showthread.php?tid=5533731][b][Guide | Tips] Getting a dog?| the thread for you! | Tips | Guides | Explanation[/b][/url] - [url=https://hackforums.net/member.php?action=profile&uid=2859279][b][color=#EFEFEF]Brusk[/color][/b][/url]\r\nBrusk has taken the time to write up a thread about man's best friend. Dogs! Inside the thread you will learn more about taking care of your dog. These things include what food to get your dog, haircuts, and even a little about their dogs body language.\r\n\r\n[url=https://hackforums.net/showthread.php?tid=5536077][b]NOOBS - Some Tips From a New member[/b][/url] - [url=https://hackforums.net/member.php?action=profile&uid=3445163][b][color=#EFEFEF]CyberWolfzz[/color][/b][/url]\r\nA member by the name of CyberWolfzz has taken the time to write up some pointers for those who are new to the Worms, Malware, and Viruses section of the forum.\r\n\r\n[url=https://hackforums.net/showthread.php?tid=5534257][b][How To] Install Nexpose on Kali 2[/b][/url] - [url=https://hackforums.net/member.php?action=profile&uid=3440314][b][color=#EFEFEF]Azaleh[/color][/b][/url]\r\nTaken from Azaleh's thread, \"Nexpose is a vulnerability managment framework, it allows us to discover, assess and act on discovered vulnerabilities, it also tells us a lot of info about the discovered vulnerabilities, weather they are exploitable and helps us write a report at the end of the assessment.\" With a step-by-step process system that Azaleh has created, you can learn how to use Nexpose yourself!\r\n\r\n[url=https://hackforums.net/showthread.php?tid=5534689][b]NOTORIOUS| Graphics Helpdesk |[/b][/url] - [url=https://hackforums.net/member.php?action=profile&uid=1655295][b][color=#EFEFEF]#Doge[/color][/b][/url]\r\n#Doge and members of the official group Notorious have created a a graphics Help Desk. Many great questions have been answered already. Do not be shy!\r\n\r\n[url=https://hackforums.net/showthread.php?tid=5535825][b][NEW MEMBERS READ] The Beginner's Guide to Hackforums by Angelus[/b][/url] - [url=https://hackforums.net/member.php?action=profile&uid=3209547][b][color=#00AAFF]♦Angelus♦[/color][/b][/url]\r\nBeginners guide to Hack Forums for new members of the forum. A short and friendly thread created to get the newer members of Hack Forums going.[/list][/list]\r\n\r\n[list][b][color=white][u]Entertaining Threads[/u][/color][/b]\r\n[list]\r\n\r\n[url=https://hackforums.net/showthread.php?tid=5532091][b]Trap Nation Hacker[/b][/url] - [url=https://hackforums.net/member.php?action=profile&uid=843689][b][color=#99FF00]Vax™[/color][/b][/url]\r\nMany people have already read up on the Trap Nation drama. If you have not done so already, you can learn more about it here.\r\n\r\n[url=https://hackforums.net/showthread.php?tid=5533584][b]If you had an IQ of 700[/b][/url] - [url=https://hackforums.net/member.php?action=profile&uid=2073436][b][color=#00AAFF]Skilō[/color][/b][/url]\r\nWhat would you do with the power of an IQ of 700?\r\n\r\n[url=https://hackforums.net/showthread.php?tid=5530909][b]HEWILLNOTDIVIDE.US (CURRENTLY THE MOST CRINGIEST THING ON THE INTERNET)[/b][/url] - [url=https://hackforums.net/member.php?action=profile&uid=1522601][b][color=#00AAFF]ZuGgY[/color][/b][/url]\r\nThis thread became very popular following the inauguration of the United States President Donald J. Trump. and has reached over 700 posts since it was created on Jan. 22.[/list][/list]\r\n\r\n[list][b][color=white][u]Member Feedback Threads[/u][/color][/b]\r\n[list]\r\n\r\nNo feedback threads were created this week.[/list][/list]\r\n\r\n[list][b][color=white][u]Contests and Giveaways[/u][/color][/b]\r\n[list]\r\n\r\n[url=https://hackforums.net/showthread.php?tid=5536533][b][Eclipse] L33T - EP1C - Award - Or Cash | Enter Now <3[/b][/url] - [url=https://hackforums.net/member.php?action=profile&uid=1680975][b][color=#EFEFEF]Regulus[/color][/b][/url]\r\nEnter this giveaway now for a chance to win an account upgrade, award, or some cash.\r\n\r\n[url=https://hackforums.net/showthread.php?tid=5533935][b]Lottery (Win up to $1000 BTC, Awards, Upgrades)[/b][/url] - [url=https://hackforums.net/member.php?action=profile&uid=3202613][b][color=#EFEFEF]Tides[/color][/b][/url]\r\nA huge giveaway being hosted by Tides. Here you have the chance to win up to $1,000! Test your luck today!\r\n\r\n[url=https://hackforums.net/showthread.php?tid=5536058][b][L33t/Ub3r] Gears Of War 4 Giveaway![/b][/url] - [url=https://hackforums.net/member.php?action=profile&uid=2681494][b][color=#00AAFF]Cʜᴀᴏs[/color][/b][/url]\r\nFans of the popular Xbox series, Gears of War rejoice! Want to win a copy of GoW 4? Now is your chance to do so![/list][/list]\r\n\r\n[list][b][color=white][u]Miscellaneous[/u][/color][/b]\r\n[list]\r\n\r\n[url=https://hackforums.net/showthread.php?tid=5534842][b]For Honor | Closed Beta | Whos in it?[/b][/url] - [url=https://hackforums.net/member.php?action=profile&uid=3229947][b][color=#00AAFF]๖ۣۜMrDark[/color][/b][/url]\r\nHad the lucky chance to obtain a For Honor closed beta code? Discuss anything about the upcoming game by Ubisoft here.\r\n\r\n[url=https://hackforums.net/showthread.php?tid=5529605][b]Writ3rs' REWIND 2016 (Edition)[/b][/url] - [url=https://hackforums.net/member.php?action=profile&uid=561239][b][color=#EFEFEF]iHydra[/color][/b][/url]\r\nIf you have not already, please take the time to read the Writ3rs' Rewind thread! In here you can find major events that happened in 2016. Something interesting for new members to look at, as well as old members to recall past memories!\r\n\r\n[url=https://hackforums.net/showthread.php?tid=5534369][b]10.2 Jailbreak Beta released.[/b][/url] - [url=https://hackforums.net/member.php?action=profile&uid=2524973][b][color=#00AAFF]Larsenpower[/color][/b][/url]\r\nInformation on the 10.2 iPhone Jailbreak has been released. Come here to watch a video explaining everything in great detail.\r\n\r\n[url=https://hackforums.net/showthread.php?tid=5535601][b]My Gundam is complete[/b][/url] - [url=https://hackforums.net/member.php?action=profile&uid=1618863][b][color=#EFEFEF]Japanese[/color][/b][/url]\r\nEveryone who is familiar with the user Japanese knows about his love for the Gundam anime series. Well, Japanese has finally completed the gift he received for Christmas. You can come check out what we are talking about in this thread!\r\n\r\n[url=https://hackforums.net/showthread.php?tid=5536003][b]PM Enhancement[/b][/url] - [url=https://hackforums.net/member.php?action=profile&uid=1306528][b][color=#EFEFEF]xadamxk[/color][/b][/url]\r\nOnce again, xadamxk has created a marvelous userscript. This useful script is titled, \"PM Enhancement\" and will do just that. Curious to know more about it? Well click here, silly!\r\n\r\n[url=https://hackforums.net/showthread.php?tid=5535860][b]My OSRS progress thread[/b][/url] - [url=https://hackforums.net/member.php?action=profile&uid=1929909][b][color=#EFEFEF]Serenity'[/color][/b][/url]\r\nAfter a few months of taking a break, the user Serenity' has started to play the popular video game Runescape again. With that being said, Serenity' has created a thread to show his progress.[/list][/list]\r\n\r\n[color=transparent]       [/color]\r\n\r\n[hr]\r\n\r\n[align=center][img]https://hackforums.news/assets/v3/Interview/328.png[/img]\r\n[color=1E90FF][size=large][font=Monotype Corsiva]Interview[/font][/size][/color] [color=white][size=large][font=Monotype Corsiva]-[/font][/size][/color] [size=large][font=Monotype Corsiva][url=https://hackforums.net/member.php?action=profile&uid=1306528]xadamxk[/url][/font][/size][spoiler=][align=left]\r\n\r\n[hr]\r\n\r\n[url=https://hackforums.net/member.php?action=profile&uid=2177496][color=#FFFFFF][b]bοxxy[/b][/color][/url]: Hello, and welcome to the 328th edition of the HF News! Would you like to give any shoutouts before we begin?\r\n[url=https://hackforums.net/member.php?action=profile&uid=1306528][color=#FFFFFF][b]xadamxk[/b][/color][/url]: Yeah all of my closed friends - Tibit, Snorlax, Clark, Harlem, Sir, Tommy, Hash G, and Steveyyy.\r\n\r\n[url=https://hackforums.net/member.php?action=profile&uid=2177496][color=#FFFFFF][b]bοxxy[/b][/color][/url]: I've noticed an impressive amount of userscripts you've made lately. What motivates you to put so much time into these, and which one(s) are you most proud of?\r\n[url=https://hackforums.net/member.php?action=profile&uid=1306528][color=#FFFFFF][b]xadamxk[/b][/color][/url]: Yeah, I have cranked out a decent amount of userscripts over Christmas break. I've always liked the idea of userscripts and being able to alter the site and improve your user experience.  As far as my favorite or most successful scripts, I think Quick Rep is up there. It was original and I got several ideas from the community for it.\r\n\r\n[url=https://hackforums.net/member.php?action=profile&uid=2177496][color=#FFFFFF][b]bοxxy[/b][/color][/url]: Very impressive indeed. So tell me about xadamxk. Who is xadamxk?\r\n[url=https://hackforums.net/member.php?action=profile&uid=1306528][color=#FFFFFF][b]xadamxk[/b][/color][/url]: I've been on the forums for several years now and I consider myself pretty inactive compared to my prime. I usually browse the lounge, RANF, mobile sections, and the web browser section for userscripts. Right now I'm just a normal college student, I've got a GF, a cat, and I hang out with friends on the weekend.\r\n\r\n[url=https://hackforums.net/member.php?action=profile&uid=2177496][color=#FFFFFF][b]bοxxy[/b][/color][/url]: Living the college dream huh? What are you studying for in college(besides beer pong, which does not count as a major)?\r\n[url=https://hackforums.net/member.php?action=profile&uid=1306528][color=#FFFFFF][b]xadamxk[/b][/color][/url]: Haha yeah, life is pretty good right now. I'm going into my Senior year at the university studying Computer Science.\r\n\r\n[url=https://hackforums.net/member.php?action=profile&uid=2177496][color=#FFFFFF][b]bοxxy[/b][/color][/url]: Interesting. Has your time here on Hack Forums been beneficial to your knowledge with computers/your studies? What kinds of things have you learned here, if any?\r\n[url=https://hackforums.net/member.php?action=profile&uid=1306528][color=#FFFFFF][b]xadamxk[/b][/color][/url]: HF was actually the reason I decided to go with CS over an engineering degree. Since that decision, I've had resources that other CS students could only dream of. I've had a number of members assist me over team viewer with programming assignments, members tutor me in discrete math/algorithms, and even used a tutorial on HF to help with an assignment. I've learned a lot from HF, but the most important thing I have learned that many members do not realize is that HF is a very valuable resource to have when in school. There are thousands of members on HF and each of them offers something to the site. As part of the community, you should use the resources that HF has to offer.\r\n\r\n[url=https://hackforums.net/member.php?action=profile&uid=2177496][color=#FFFFFF][b]bοxxy[/b][/color][/url]: Great Response, thank you for that. You've been on HF for quite some time now, seeing your join date in 2011 coming up on 6 years now in April(Congrats by the way.) What made you initially join Hack Forums, and do you think HF has gotten better, worse, or not much change in terms of quality/experience?\r\n[url=https://hackforums.net/member.php?action=profile&uid=1306528][color=#FFFFFF][b]xadamxk[/b][/color][/url]: I joined because one of my good friends told me about the site. Overall, HF has improved. There are more features, there are more moderators, and there is a wider variety of members. I miss some of the old member base and the way things were years ago, but all in all, things have improved.\r\n\r\n[url=https://hackforums.net/member.php?action=profile&uid=2177496][color=#FFFFFF][b]bοxxy[/b][/color][/url]: Ah, I see. Just a few more questions if you don't mind before we wrap this one up. I want to ask you about groups. What official groups here on Hack Forums have you been in? Any favorites?\r\n[url=https://hackforums.net/member.php?action=profile&uid=1306528][color=#FFFFFF][b]xadamxk[/b][/color][/url]: I mind damnit. At one time or another I've been in most private groups. The Empire, The Alliance, The Brotherhood, and (at the time) The Alliance were my favorites. Groups have changed a lot over the years, I'm hoping the pick back up with the recent group changes.\r\n\r\n[url=https://hackforums.net/member.php?action=profile&uid=2177496][color=#FFFFFF][b]bοxxy[/b][/color][/url]: Groups have definitely changed, that's for certain. Alright, last ones I promise. What are your most active and/or favorite sections we have here on Hack Forums, and do you think Hack Forums could use another specific section?(Ex. Car Section is favored by many but denied)\r\n[url=https://hackforums.net/member.php?action=profile&uid=1306528][color=#FFFFFF][b]xadamxk[/b][/color][/url]: I mostly browse in the Lounge, RANF, iOS section, Web Browsers (Userscripts), and private groups. As far as additional sections, I know a car section has been one of the most popular section suggestions. I personally do not think HF has the kind of activity to warrant a new section, but time will tell I guess. I know there is a user group that is focused on that topic now, so maybe that will help.\r\n\r\n[url=https://hackforums.net/member.php?action=profile&uid=2177496][color=#FFFFFF][b]bοxxy[/b][/color][/url]: Definitely. Well, that'll be all for today. Anything else you would like to add?\r\n[url=https://hackforums.net/member.php?action=profile&uid=1306528][color=#FFFFFF][b]xadamxk[/b][/color][/url]: nah that'll be good I guess! thanks noob\r\n\r\n[/align][/spoiler][/align]\r\n\r\n[hr]\r\n\r\n[color=transparent]       [/color][/size][/font]",
      "subject": "Hack Forums News // Edition 328"
    },
    {
      "pid": "53976564",
      "uid": "561239",
      "dateline": "1485906067",
      "message": "[font=Trebuchet MS][size=1][color=transparent]       [/color]\n\n[align=center][img]http://hackforums.news/assets/v3/2-303.png[/img][/align]\n\n[color=transparent]       [/color]\n\n[align=center][img]http://hackforums.news/assets/v3/SupportHFN.png[/img][/align]\n\n[align=center]We publish the HF News every week yet we have aged members who don't even know we exist! Wear any of the signatures listed below to support us and spread the word about HF News, HF Wiki, and Writers altogether. \n\n[color=white][spoiler=[b]Support Signatures[/b]]\n\n[color=white][b]-1-[/b][/color]\n[url=http://bitly.com/1FnhESq][img]http://i.imgur.com/pdoOihY.png[/img][/url]\n[code][align=center][url=http://bitly.com/1FnhESq][img]http://i.imgur.com/pdoOihY.png[/img][/url][/align][/code]\n\n[color=white][b]-2-[/b][/color]\n[url=http://bitly.com/1FnhESq][img]https://i.imgur.com/VTs6K6A.gif[/img][/url]\n[code][align=center][url=http://bitly.com/1FnhESq][img]https://i.imgur.com/VTs6K6A.gif[/img][/url][/align][/code]\n\n[color=white][b]-3-[/b][/color]\n[url=http://bitly.com/1FnhESq][img]https://i.imgur.com/hkLhk6f.gif[/img][/url]\n[code][align=center][url=http://bitly.com/1FnhESq][img]https://i.imgur.com/hkLhk6f.gif[/img][/url][/align][/code]\n\n[color=white][b]-4-[/b][/color]\n[url=http://bitly.com/1FnhESq][img]https://i.imgur.com/ceUBlwQ.gif[/img][/url]\n[code][align=center][url=http://bitly.com/1FnhESq][img]https://i.imgur.com/ceUBlwQ.gif[/img][/url][/align][/code]\n\n[color=white][b]-5-[/b][/color]\n[url=http://bitly.com/1FnhESq][img]https://i.imgur.com/54dbXHH.gif[/img][/url]\n[code][align=center][url=http://bitly.com/1FnhESq][img]http://i.imgur.com/pdoOihY.png[/img][/url][/align][/code]\n\n[color=white][b]-6-[/b][/color]\n[url=http://bitly.com/1FnhESq][img]https://i.imgur.com/oowqdqM.gif[/img][/url]\n[code][align=center][url=http://bitly.com/1FnhESq][img]https://i.imgur.com/oowqdqM.gif[/img][/url][/align][/code]\n\n[color=white][b]-7-[/b][/color]\n[url=http://bitly.com/1FnhESq][img]https://i.imgur.com/KssvPNL.gif[/img][/url]\n[code][align=center][url=http://bitly.com/1FnhESq][img]https://i.imgur.com/KssvPNL.gif[/img][/url][/align][/code]\n[/spoiler][/color][/align]\n\n[color=transparent]       [/color]\n\n[align=center][img]http://hackforums.news/assets/v3/Memo.png[/img][/align]\n\n[b][color=white]Tommy[/color][/b]\nTROLOLOLOLOL!\n\n[b][color=white]Change or Die[/color][/b]\nWe are currently going through a backend change of our system. For the next few editions, sections may be missing, editions published late or skipped, etc. Consider us as \"Under Construction\" as we move towards our new system. \n\n[color=transparent]   [/color]\n\n[align=center][img]https://hackforums.news/assets/v3/WorldNews.png[/img][/align]\n\n[b][color=white]US Withdraws from Trans-Pacific Trade Deal[/color][/b]\nFollowing a campaign promise, Donald Trump signed an executive order that withdrew the United States from the Trans-Pacific Partnership (TPP). The deal was intended to link 12 nations to a complex set of trade rules. This move is part of Trump’s “America First” stance, which pushes for a more aggressive stance against foreign competitors. The TPP was former President Barack Obama’s signature trade deal.[i][size=x-small][url=https://www.nytimes.com/2017/01/23/us/politics/tpp-trump-trade-nafta.html] >>Source[/url][/size][/i]\n\n[b][color=white]Mexicans Launch Boycotts Against US Companies[/color][/b]\nIn a method of protest against the United States’ new administration, Mexicans are planning to boycott American products. The boycott was spurred by Trump’s push for a border wall, deportations, and new trade deals. This boycott follows the Mexican president’s cancellation of a meeting between the two nations. Mexico has an economy that is only one-tenth the size of the US, but the nation looks as if it will not go down without a fight. Polls in Mexico show that the president of the United States has a 3% favorability rating among Mexican citizens.[i][size=x-small][url=http://time.com/4651464/mexico-donald-trump-boycott-protests/] >>Source[/url][/size][/i]\n\n[b][color=white]New Zealand and Denmark Declared the “Least Corrupt” Countries in the World[/color][/b]\nTransparency International, a Berlin-based anti-corruption organization, has released its “Corruption Perception Index” for the year of 2016. There are 176 countries listed in the index, and both Denmark and New Zealand hold the highest ranks. Since the mid-1990s, when this annual list started, New Zealand has always ranked very high in the list. Nordic countries, such as Denmark, generally place high in the rankings as well. Overall, sixty-nine percent of the countries listed in the index scored less than a 50, where 0 is considered to be extremely corrupt, and 100 is considered “very clean.” Both Denmark and New Zealand received a score of 90. Transparency International uses World Bank data, the World Economic Forum, and other institutions to form their rankings. [i][size=x-small][url=http://www.stuff.co.nz/business/88770772/new-zealand-and-denmark-deemed-the-least-corrupt-countries-in-the-world] >>Source[/url][/size][/i]\n\n[color=transparent]    [/color]\n\n[align=center][img]https://hackforums.news/assets/v3/TechNews/Gladly.png[/img][/align]\n[align=left]\n[url=http://www.fiercecable.com/cable/3d-tv-officially-dead-as-sony-and-lg-stop-making-sets][b]3D TV Meets its Demise[/b][/url]\nWhat was once thought to be the future of television and media, 3D televisions are finally meeting their demise with an announcement from Sony and LG - 3D TV's biggest manufacturers, stating that they will no longer be produced. Along with this, 3D capability will no longer be offered in their newer televisions either. Tim Alessi, LG's director of new product development, stated that the feature was never fully embraced, and just not something many consumers factored in when purchasing a new TV. Instead, he claims LG will focus on other features consumers are looking for. The announcement seems late to many, as 3D content is few and far between, and most 3D channels have been off the air for years, including DirecTV, ESPN, Discovery, and other major channels. The focus away from clunky glasses and headaches is seen as a step in the right direction from both manufacturers and customers everywhere.\n\n[url=https://electrek.co/2017/01/23/tesla-mira-loma-powerpack-station-southern-california-edison/][b]Tesla Launches World's Biggest Power Station [/b][/url]\nBoasting a massive 80 MWh, Tesla has created what is the world's largest power station in Southern California, in association with Southern California Edison. Dubbed the Powerpack Station, the facility is capable of powering a whopping 2,500 households or more for a day. The project makes use of new a new inverter created by Tesla themselves, that increases power density and efficiency of the battery packs in the system. The system will be used to power homes when electricity is in high demand in the area, and will charge when electricity is not in high demand, typically at odd hours of the day. This results in their partner, Southern California Edison (SCE), having to depend less and less on natural gas plants for extra energy when it is needed. The Powerpack Station will be used in conjunction with SCE's traditional grid which s estimated to cover over 15 million people.\n\n[url=http://www.theverge.com/circuitbreaker/2017/1/24/14368622/raspberry-pi-alternative-tinker-board-asus-4k][b]Tinker Board: Asus' Answer to the Raspberry Pi [/b][/url]\nAsus is getting into the niche mini computer, a field dominated by devices such as the Arduino and the Raspberry Pi, with an answer of their own: the Tinker Board. Despite it being a bit pricier than the Pi at $68 USD, the Tinker Board features many slight upgrades over the Pi. Enthusiasts will be delighted to see Asus' device features double the RAM of the Raspberry Pi 3B, gigabit LAN, a 1.8 GHz quad-cure processor, and some other neat upgrades over other devices. Thanks to the GPU, RAM, and a 2.0 HDMI port, the Tinker Board has access to 4K video and H.264/H.265 video encoding, making it great for anyone looking for a 4K capable media center. To achieve this, consumers could use Debian Linux, which is also supported by the Tinker Board and could be a key selling point for prospective buyers.\n[/align]\n\n[color=transparent]       [/color]\n\n[align=center][img]https://hackforums.news/assets/v3/HackingNews.png[/img][/align]\n\n[b][color=white]Over 70% of Washington, D.C. Public CTV System Hacked[/color][/b]\nA few days before Donald Trump's inauguration, over 70 percent of CCTV storage systems in Washington D.C. were hacked. It appears to be ransomware, which is the easiest way for a hacker to get money without much labor. 123 out of the 187 federal video recorders were infected, and each control between one and four public security cameras in D.C. The system was then offline from January 12th until the 15th. Officials took the systems offline, removed the malware, and restored them to working order. No ransoms were paid.[i][size=x-small][url=http://www.hackersnewsbulletin.com/2017/01/washington-ctv-system-hacked.html] >>Source[/url][/size][/i]\n\n[b][color=white]WikiLeaks Asks Hackers to Leak Trump's Tax Returns[/color][/b]\nAfter President Donald Trump went back on numerous promises to release his tax returns, WikiLeaks has asked people to get their hands on them and anonymously send them into WikiLeaks. The call-to-action came after Kellyanne Conway, one of Trump's senior advisers, told ABC's This Week, \"The White House response is that he's not going to release his tax returns. We litigated this all through the election.\" A petition opened on the day of his inauguration which asks that Trump release his full tax returns. It got 262,131 signatures--out of only a needed 100,000.[i][size=x-small][url=http://www.computerworld.com/article/3160489/security/wikileaks-urges-hackers-to-leak-trumps-tax-returns.html] >>Source[/url][/size][/i]\n\n[b][color=white]It's Now Illegal to Bypass China's Firewall with a VPN[/color][/b]\nChina imposes a strict censorship on its citizens with what's called the Great Firewall of China. The system censors the internet and denies citizens access to certain foreign websites. The firewall bans 171 out of the 1000 top websites online--some of which are Facebook, Twitter, Dropbox, and Tumblr. China recently announced a shutdown of VPNs across the country, making it even harder to bypass the filter. China's Ministry of Industry and Information Technology, has introduced an act that makes running local VPN services illegal without a license from the government. This renders VPN services in the country with over 730 million users now illegal.[i][size=x-small][url=http://www.hackersnewsbulletin.com/2017/01/china-fireball-vpn.html] >>Source[/url][/size][/i]\n\n[color=transparent]   [/color][/size][/font]",
      "subject": "*"
    },
    {
      "pid": "53977013",
      "uid": "561239",
      "dateline": "1485907970",
      "message": "[font=Trebuchet MS][size=1][color=transparent]       [/color]\n\n[align=center][img]https://www.hackforums.news/assets/v3/3-301.png[/img][/align]\n\n[color=transparent]       [/color]\n\n[align=center][img]http://www.hackforums.news/assets/v3/Spotlight.png[/img][/align]\n\n[align=center][url=https://hackforums.net/showthread.php?tid=3590292][b][color=white]WoW and Lineage II[/color][/b][/url]\n[img]http://hackforums.news/assets/v3/Spotlight/328-1.png[/img]\nBy [b][url=https://hackforums.net/member.php?action=profile&uid=1551705][color=#99FF00]ArdentFX[/color][/url][/b][/align]\n\n[align=center][url=https://hackforums.net/showthread.php?tid=5529672][b][color=white]Some Ugly Shit[/color][/b][/url]\n[img]http://hackforums.news/assets/v3/Spotlight/328-2.png[/img]\nBy [b][url=https://hackforums.net/member.php?action=profile&uid=776749][color=#00AAFF]Motusora[/color][/url][/b][/align]\n\n[align=center][i]Want to showcase your own battlestation? [url=https://hackforums.net/private.php?action=send&uid=561239&subject=HFN%20Battlestation&message=Here%20are%20images%20of%20my%20battlestation:%20]Submit yours now![/url][/i][/align]\n[color=transparent]         [/color][/size][/font]",
      "subject": "*"
    }
  ]
}